Workbook
Name ColumnTitle1: #REF!
Name ColumnTitle1: #REF!
Name ColumnTitle1: #REF!
Name ColumnTitle1: #REF!
Name ColumnTitle1: #REF!
Name ColumnTitle1: #REF!
Name Con_OnOff: #REF!
Name CONTENT: #REF!
Name CONTENT: #REF!
Name CONTENT: #REF!
Name CONTENT: #REF!
Name CONTENT: #REF!
Name CONTENT: #REF!
Name Currency_Symbol: #REF!
Name DD_TS_Denom: #REF!
Name Denomination_Selected: #REF!
Name EndingBalance: -FV(InterestRate/12,'اسعار الخدمات'!PaymentNumber,-'اسعار الخدمات'!MonthlyPayment,LoanAmount)
Name EndingBalance: -FV([0]!InterestRate/12,'اسعار الخدمات '!PaymentNumber,-'اسعار الخدمات '!MonthlyPayment,[0]!LoanAmount)
Name EndingBalance: -FV(InterestRate/12,'تحليل التعادل '!PaymentNumber,-'تحليل التعادل '!MonthlyPayment,LoanAmount)
Name EndingBalance: -FV(InterestRate/12,PaymentNumber,-MonthlyPayment,LoanAmount)
Name Gov_OnOff: #REF!
Name HeaderRow: ROW(#REF!)
Name HeaderRow: ROW(#REF!)
Name InterestAmt: -IPMT(InterestRate/12,'اسعار الخدمات'!PaymentNumber,NumberOfPayments,LoanAmount)
Name InterestAmt: -IPMT([0]!InterestRate/12,'اسعار الخدمات '!PaymentNumber,[0]!NumberOfPayments,[0]!LoanAmount)
Name InterestAmt: -IPMT(InterestRate/12,'تحليل التعادل '!PaymentNumber,NumberOfPayments,LoanAmount)
Name InterestAmt: -IPMT(InterestRate/12,PaymentNumber,NumberOfPayments,LoanAmount)
Name InterestRate: #REF!
Name IQ_CH: 110000
Name IQ_CQ: 5000
Name IQ_CY: 10000
Name IQ_DAILY: 500000
Name IQ_FH: 100000
Name IQ_FQ: 500
Name IQ_FY: 1000
Name IQ_LTM: 2000
Name IQ_MONTH: 15000
Name IQ_NTM: 6000
Name IQ_WEEK: 50000
Name IQ_YTD: 3000
Name LastCol: COUNTA(#REF!)
Name LastCol: COUNTA(#REF!)
Name LastRow: MATCH(9.99E+307,#REF!)
Name LastRow: MATCH(9.99E+307,#REF!)
Name LoanAmount: #REF!
Name LoanIsGood: IF(LoanAmount*InterestRate*LoanYears*LoanStartDate>0,1,0)
Name LoanIsGood: IF([0]!LoanAmount*[0]!InterestRate*[0]!LoanYears*[0]!LoanStartDate>0,1,0)
Name LoanIsGood: IF(LoanAmount*InterestRate*LoanYears*LoanStartDate>0,1,0)
Name LoanIsGood: IF(LoanAmount*InterestRate*LoanYears*LoanStartDate>0,1,0)
Name LoanIsNotPaid: IF('اسعار الخدمات'!PaymentNumber<=NumberOfPayments,1,0)
Name LoanIsNotPaid: IF('اسعار الخدمات '!PaymentNumber<=[0]!NumberOfPayments,1,0)
Name LoanIsNotPaid: IF('تحليل التعادل '!PaymentNumber<=NumberOfPayments,1,0)
Name LoanIsNotPaid: IF(PaymentNumber<=NumberOfPayments,1,0)
Name LoanStartDate: #REF!
Name LoanValue: -FV(InterestRate/12,'اسعار الخدمات'!PaymentNumber-1,-'اسعار الخدمات'!MonthlyPayment,LoanAmount)
Name LoanValue: -FV([0]!InterestRate/12,'اسعار الخدمات '!PaymentNumber-1,-'اسعار الخدمات '!MonthlyPayment,[0]!LoanAmount)
Name LoanValue: -FV(InterestRate/12,'تحليل التعادل '!PaymentNumber-1,-'تحليل التعادل '!MonthlyPayment,LoanAmount)
Name LoanValue: -FV(InterestRate/12,PaymentNumber-1,-MonthlyPayment,LoanAmount)
Name LoanYears: #REF!
Name LU_Debt_type: #REF!

Sheet تحليل التعادل 
P3: الرجوع إلى جدول المحتويات
F7: السنة 1 | G7: السنة 2 | H7: السنة 3 | I7: السنة 4 | J7: السنة 5
D9: الإيرادات | F9: ='قائمة الدخل التقديرية'!D6 -> #VALUE! | G9: ='قائمة الدخل التقديرية'!E6 -> #VALUE! | H9: ='قائمة الدخل التقديرية'!F6 -> #VALUE! | I9: ='قائمة الدخل التقديرية'!G6 -> #VALUE! | J9: ='قائمة الدخل التقديرية'!H6 -> #VALUE!
D10: التكاليف المتغيرة | F10: ='قائمة الدخل التقديرية'!D10 -> 270664.8 | G10: ='قائمة الدخل التقديرية'!E10 -> 276078.1 | H10: ='قائمة الدخل التقديرية'!F10 -> 281599.66 | I10: ='قائمة الدخل التقديرية'!G10 -> 287231.65 | J10: ='قائمة الدخل التقديرية'!H10 -> 292976.28
D11: التكاليف الثابتة | F11: ='قائمة الدخل التقديرية'!D20 -> #REF! | G11: ='قائمة الدخل التقديرية'!E20 -> #REF! | H11: ='قائمة الدخل التقديرية'!F20 -> 18002337 | I11: ='قائمة الدخل التقديرية'!G20 -> 18006297 | J11: ='قائمة الدخل التقديرية'!H20 -> 18010336
D12: نسبة هامش المساهمة | F12: =100%-(F10/F9) -> #VALUE! | G12: =100%-(G10/G9) -> #VALUE! | H12: =100%-(H10/H9) -> #VALUE! | I12: =100%-(I10/I9) -> #VALUE! | J12: =100%-(J10/J9) -> #VALUE!
D13: نقطة التعادل بالقيمة | F13: =F11/F12 -> #REF! | G13: =G11/G12 -> #REF! | H13: =H11/H12 -> #VALUE! | I13: =I11/I12 -> #VALUE! | J13: =J11/J12 -> #VALUE!

Sheet قائمة الدخل التقديرية
C2: قائمة الدخل التقديرية
C4: الإيرادات | D4: السنة 1 | E4: السنة 2 | F4: السنة 3 | G4: السنة 4 | H4: السنة 5
C5: إيرادات خدمات النادي | D5: ='تقدير الإيرادات '!I9 -> #VALUE! | E5: ='تقدير الإيرادات '!F17 -> #VALUE! | F5: ='تقدير الإيرادات '!G17 -> #VALUE! | G5: ='تقدير الإيرادات '!H17 -> #VALUE! | H5: ='تقدير الإيرادات '!I17 -> #VALUE!
C6: إجمالي الإيردات | D6: =SUM(D5:D5) -> #VALUE! | E6: =SUM(E5:E5) -> #VALUE! | F6: =SUM(F5:F5) -> #VALUE! | G6: =SUM(G5:G5) -> #VALUE! | H6: =SUM(H5:H5) -> #VALUE!
C7: يطرح المصاريف المتغيرة
C8: رواتب المشرفين والمدربين | D8: =SUM('الدراسة الفنية '!G7:G9,'الدراسة الفنية '!G11,'الدراسة الفنية '!G15:G17,'الدراسة الفنية '!G19,'الدراسة الفنية '!G23:G25,'الدراسة الفنية '!G27,'الدراسة الفنية '!G31:G33,'الدراسة الفنية '!G35) -> 216000 | E8: =D8*(1+'الدراسة المالية'!$D5) -> 220320 | F8: =E8*(1+'الدراسة المالية'!$D5) -> 224726.4 | G8: =F8*(1+'الدراسة المالية'!$D5) -> 229220.93 | H8: =G8*(1+'الدراسة المالية'!$D5) -> 233805.35
C9: مصاريف تشغيلية متغيرة | D9: ='الدراسة الفنية '!I137 -> 54664.8 | E9: =D9*(1+'الدراسة المالية'!$D5) -> 55758.096 | F9: =E9*(1+'الدراسة المالية'!$D5) -> 56873.258 | G9: =F9*(1+'الدراسة المالية'!$D5) -> 58010.723 | H9: =G9*(1+'الدراسة المالية'!$D5) -> 59170.938
C10: إجمالي تكلفة الإيرادات | D10: =SUM(D8:D9) -> 270664.8 | E10: =SUM(E8:E9) -> 276078.1 | F10: =SUM(F8:F9) -> 281599.66 | G10: =SUM(G8:G9) -> 287231.65 | H10: =SUM(H8:H9) -> 292976.28
C11: مجمل الربح | D11: =D6-D10 -> #VALUE! | E11: =E6-E10 -> #VALUE! | F11: =F6-F10 -> #VALUE! | G11: =G6-G10 -> #VALUE! | H11: =H6-H10 -> #VALUE!
C12: يطرح المصاريف الأخرى الثابتة
C13: رواتب الإداريين | D13: =SUM('الدراسة الفنية '!G6,'الدراسة الفنية '!G10,'الدراسة الفنية '!G14,'الدراسة الفنية '!G18,'الدراسة الفنية '!G22,'الدراسة الفنية '!G26,'الدراسة الفنية '!G30,'الدراسة الفنية '!G34) -> 114000 | E13: =D13*(1+'الدراسة المالية'!$D5) -> 116280 | F13: =E13*(1+'الدراسة المالية'!$D5) -> 118605.6 | G13: =F13*(1+'الدراسة المالية'!$D5) -> 120977.71 | H13: =G13*(1+'الدراسة المالية'!$D5) -> 123397.27
C14: المصاريف التشغيلية الثابتة | D14: ='الدراسة الفنية '!J137 -> 76301.28 | E14: =D14*(1+'الدراسة المالية'!$D5) -> 77827.306 | F14: =E14*(1+'الدراسة المالية'!$D5) -> 79383.852 | G14: =F14*(1+'الدراسة المالية'!$D5) -> 80971.529 | H14: =G14*(1+'الدراسة المالية'!$D5) -> 82590.959
C15: مصاريف الاستهلاك | D15: =SUM('الدراسة الفنية '!I53,'الدراسة الفنية '!I79,'الدراسة الفنية '!I102) -> 14751613 | E15: =D15 -> 14751613 | F15: =E15 -> 14751613 | G15: =F15 -> 14751613 | H15: =G15 -> 14751613
C16: مصاريف الصيانة | D16: =SUM('الدراسة الفنية '!I54,'الدراسة الفنية '!I80,'الدراسة الفنية '!I103) -> 2979534.9 | E16: =D16 -> 2979534.9 | F16: =E16 -> 2979534.9 | G16: =F16 -> 2979534.9 | H16: =G16 -> 2979534.9
C17: مصاريف الايجار | F17: ='الدراسة الفنية '!$H150 -> 73200 | G17: ='الدراسة الفنية '!$H150 -> 73200 | H17: ='الدراسة الفنية '!$H150 -> 73200
C18: المصاريف القانونية | D18: =#REF!/2 -> #REF! | E18: =#REF!/2 -> #REF! | F18: - | G18: - | H18: -
C19: مصاريف الحملة التسويقية | D19: =#REF!/2 -> #REF! | E19: =#REF!/2 -> #REF! | F19: - | G19: - | H19: -
C20: إجمالي المصاريف الأخرى الثابتة | D20: =SUM(D13:D19) -> #REF! | E20: =SUM(E13:E19) -> #REF! | F20: =SUM(F13:F19) -> 18002337 | G20: =SUM(G13:G19) -> 18006297 | H20: =SUM(H13:H19) -> 18010336
C21: صافي الأرباح قبل الضريبة | D21: =D11-D20 -> #VALUE! | E21: =E11-E20 -> #VALUE! | F21: =F11-F20 -> #VALUE! | G21: =G11-G20 -> #VALUE! | H21: =H11-H20 -> #VALUE!
C22: مصروف الضريبة | D22: =D21*'الدراسة المالية'!$D6 -> #VALUE! | E22: =E21*'الدراسة المالية'!$D6 -> #VALUE! | F22: =F21*'الدراسة المالية'!$D6 -> #VALUE! | G22: =G21*'الدراسة المالية'!$D6 -> #VALUE! | H22: =H21*'الدراسة المالية'!$D6 -> #VALUE!
C23: صافي الأرباح النهائية | D23: =H46 -> #VALUE! | E23: =O46 -> #VALUE! | F23: =V46 -> #VALUE! | G23: =AC46 -> #VALUE! | H23: =AJ46 -> #VALUE!
C26: قائمة الدخل التقديرية وفقا لكل قسم | J26: قائمة الدخل التقديرية وفقا لكل قسم | Q26: قائمة الدخل التقديرية وفقا لكل قسم | X26: قائمة الدخل التقديرية وفقا لكل قسم | AE26: قائمة الدخل التقديرية وفقا لكل قسم
C27: السنة 1 | J27: السنة 2 | Q27: السنة 3 | X27: السنة 4 | AE27: السنة 5
C28: الإيرادات | D28: المسبح | E28: البادل | F28: الملعب متعدد الأغراض | G28: الصالة الرياضية | H28: الإجمالي | J28: الإيرادات | K28: المسبح | L28: البادل | M28: الملعب متعدد الأغراض | N28: الصالة الرياضية | O28: الإجمالي | Q28: الإيرادات | R28: المسبح | S28: البادل | T28: الملعب متعدد الأغراض | U28: الصالة الرياضية | V28: الإجمالي | X28: الإيرادات | Y28: المسبح | Z28: البادل | AA28: الملعب متعدد الأغراض | AB28: الصالة الرياضية | AC28: الإجمالي | AE28: الإيرادات | AF28: المسبح | AG28: البادل | AH28: الملعب متعدد الأغراض | AI28: الصالة الرياضية | AJ28: الإجمالي
C29: إيرادات خدمات النادي | D29: ='تقدير الإيرادات '!I5 -> 272700 | E29: ='تقدير الإيرادات '!I6 -> #VALUE! | F29: ='تقدير الإيرادات '!I7 -> 249900 | G29: ='تقدير الإيرادات '!I8 -> 191700 | H29: =SUM(D29:G29) -> #VALUE! | J29: إيرادات خدمات النادي | K29: ='تقدير الإيرادات '!F13 -> 291789 | L29: ='تقدير الإيرادات '!F14 -> #VALUE! | M29: ='تقدير الإيرادات '!F15 -> 267393 | N29: ='تقدير الإيرادات '!F16 -> 205119 | O29: =SUM(K29:N29) -> #VALUE! | Q29: إيرادات خدمات النادي | R29: ='تقدير الإيرادات '!G13 -> 312214.23 | S29: ='تقدير الإيرادات '!G14 -> #VALUE! | T29: ='تقدير الإيرادات '!G15 -> 286110.51 | U29: ='تقدير الإيرادات '!G16 -> 219477.33 | V29: =SUM(R29:U29) -> #VALUE! | X29: إيرادات خدمات النادي | Y29: ='تقدير الإيرادات '!H13 -> 334069.23 | Z29: ='تقدير الإيرادات '!H14 -> #VALUE! | AA29: ='تقدير الإيرادات '!H15 -> 306138.25 | AB29: ='تقدير الإيرادات '!H16 -> 234840.74 | AC29: =SUM(Y29:AB29) -> #VALUE! | AE29: إيرادات خدمات النادي | AF29: ='تقدير الإيرادات '!I13 -> 357454.07 | AG29: ='تقدير الإيرادات '!I14 -> #VALUE! | AH29: ='تقدير الإيرادات '!I15 -> 327567.92 | AI29: ='تقدير الإيرادات '!I16 -> 251279.6 | AJ29: =SUM(AF29:AI29) -> #VALUE!
C30: إجمالي الإيردات | D30: =SUM(D29:D29) -> 272700 | E30: =SUM(E29:E29) -> #VALUE! | F30: =SUM(F29:F29) -> 249900 | G30: =SUM(G29:G29) -> 191700 | H30: =SUM(H29:H29) -> #VALUE! | J30: إجمالي الإيردات | K30: =SUM(K29:K29) -> 291789 | L30: =SUM(L29:L29) -> #VALUE! | M30: =SUM(M29:M29) -> 267393 | N30: =SUM(N29:N29) -> 205119 | O30: =SUM(O29:O29) -> #VALUE! | Q30: إجمالي الإيردات | R30: =SUM(R29:R29) -> 312214.23 | S30: =SUM(S29:S29) -> #VALUE! | T30: =SUM(T29:T29) -> 286110.51 | U30: =SUM(U29:U29) -> 219477.33 | V30: =SUM(V29:V29) -> #VALUE! | X30: إجمالي الإيردات | Y30: =SUM(Y29:Y29) -> 334069.23 | Z30: =SUM(Z29:Z29) -> #VALUE! | AA30: =SUM(AA29:AA29) -> 306138.25 | AB30: =SUM(AB29:AB29) -> 234840.74 | AC30: =SUM(AC29:AC29) -> #VALUE! | AE30: إجمالي الإيردات | AF30: =SUM(AF29:AF29) -> 357454.07 | AG30: =SUM(AG29:AG29) -> #VALUE! | AH30: =SUM(AH29:AH29) -> 327567.92 | AI30: =SUM(AI29:AI29) -> 251279.6 | AJ30: =SUM(AJ29:AJ29) -> #VALUE!
C31: يطرح المصاريف المتغيرة | D31: =D30/$H30 -> #VALUE! | E31: =E30/$H30 -> #VALUE! | F31: =F30/$H30 -> #VALUE! | G31: =G30/$H30 -> #VALUE! | H31: =H30/$H30 -> #VALUE! | J31: يطرح المصاريف المتغيرة | K31: =K30/$H30 -> #VALUE! | L31: =L30/$H30 -> #VALUE! | M31: =M30/$H30 -> #VALUE! | N31: =N30/$H30 -> #VALUE! | O31: =O30/$H30 -> #VALUE! | Q31: يطرح المصاريف المتغيرة | R31: =R30/$H30 -> #VALUE! | S31: =S30/$H30 -> #VALUE! | T31: =T30/$H30 -> #VALUE! | U31: =U30/$H30 -> #VALUE! | V31: =V30/$H30 -> #VALUE! | X31: يطرح المصاريف المتغيرة | Y31: =Y30/$H30 -> #VALUE! | Z31: =Z30/$H30 -> #VALUE! | AA31: =AA30/$H30 -> #VALUE! | AB31: =AB30/$H30 -> #VALUE! | AC31: =AC30/$H30 -> #VALUE! | AE31: يطرح المصاريف المتغيرة | AF31: =AF30/$H30 -> #VALUE! | AG31: =AG30/$H30 -> #VALUE! | AH31: =AH30/$H30 -> #VALUE! | AI31: =AI30/$H30 -> #VALUE! | AJ31: =AJ30/$H30 -> #VALUE!
C32: رواتب المشرفين والمدربين | D32: =SUM('الدراسة الفنية '!G7:G9,'الدراسة الفنية '!G11) -> 54000 | E32: =SUM('الدراسة الفنية '!G15:G17,'الدراسة الفنية '!G19) -> 54000 | F32: =SUM('الدراسة الفنية '!G23:G25,'الدراسة الفنية '!G27) -> 54000 | G32: =SUM('الدراسة الفنية '!G31:G33,'الدراسة الفنية '!G35) -> 54000 | H32: =SUM(D32:G32) -> 216000 | J32: رواتب المشرفين والمدربين | K32: =SUM('الدراسة الفنية '!G7:G9,'الدراسة الفنية '!G11)*(1+'الدراسة المالية'!$D5) -> 55080 | L32: =E32*1.02 -> 55080 | M32: =F32*1.02 -> 55080 | N32: =G32*1.02 -> 55080 | O32: =SUM(K32:N32) -> 220320 | Q32: رواتب المشرفين والمدربين | R32: =K32*1.02 -> 56181.6 | S32: =L32*1.02 -> 56181.6 | T32: =M32*1.02 -> 56181.6 | U32: =N32*1.02 -> 56181.6 | V32: =SUM(R32:U32) -> 224726.4 | X32: رواتب المشرفين والمدربين | Y32: =R32*1.02 -> 57305.232 | Z32: =S32*1.02 -> 57305.232 | AA32: =T32*1.02 -> 57305.232 | AB32: =U32*1.02 -> 57305.232 | AC32: =SUM(Y32:AB32) -> 229220.93 | AE32: رواتب المشرفين والمدربين | AF32: =Y32*1.02 -> 58451.337 | AG32: =Z32*1.02 -> 58451.337 | AH32: =AA32*1.02 -> 58451.337 | AI32: =AB32*1.02 -> 58451.337 | AJ32: =SUM(AF32:AI32) -> 233805.35
C33: مصاريف تشغيلية متغيرة | D33: ='الدراسة الفنية '!$I137/4 -> 13666.2 | E33: ='الدراسة الفنية '!$I137/4 -> 13666.2 | F33: ='الدراسة الفنية '!$I137/4 -> 13666.2 | G33: ='الدراسة الفنية '!$I137/4 -> 13666.2 | H33: =SUM(D33:G33) -> 54664.8 | J33: مصاريف تشغيلية متغيرة | K33: =('الدراسة الفنية '!$I137/4)*(1+'الدراسة المالية'!$D5) -> 13939.524 | L33: =('الدراسة الفنية '!$I137/4)*(1+'الدراسة المالية'!$D5) -> 13939.524 | M33: =('الدراسة الفنية '!$I137/4)*(1+'الدراسة المالية'!$D5) -> 13939.524 | N33: =('الدراسة الفنية '!$I137/4)*(1+'الدراسة المالية'!$D5) -> 13939.524 | O33: =SUM(K33:N33) -> 55758.096 | Q33: مصاريف تشغيلية متغيرة | R33: =K33*1.02 -> 14218.314 | S33: =L33*1.02 -> 14218.314 | T33: =M33*1.02 -> 14218.314 | U33: =N33*1.02 -> 14218.314 | V33: =SUM(R33:U33) -> 56873.258 | X33: مصاريف تشغيلية متغيرة | Y33: =R33*1.02 -> 14502.681 | Z33: =S33*1.02 -> 14502.681 | AA33: =T33*1.02 -> 14502.681 | AB33: =U33*1.02 -> 14502.681 | AC33: =SUM(Y33:AB33) -> 58010.723 | AE33: مصاريف تشغيلية متغيرة | AF33: =Y33*1.02 -> 14792.734 | AG33: =Z33*1.02 -> 14792.734 | AH33: =AA33*1.02 -> 14792.734 | AI33: =AB33*1.02 -> 14792.734 | AJ33: =SUM(AF33:AI33) -> 59170.938
C34: إجمالي تكلفة الإيرادات | D34: =SUM(D32:D33) -> 67666.2 | E34: =SUM(E32:E33) -> 67666.2 | F34: =SUM(F32:F33) -> 67666.2 | G34: =SUM(G32:G33) -> 67666.2 | H34: =SUM(H32:H33) -> 270664.8 | J34: إجمالي تكلفة الإيرادات | K34: =SUM(K32:K33) -> 69019.524 | L34: =SUM(L32:L33) -> 69019.524 | M34: =SUM(M32:M33) -> 69019.524 | N34: =SUM(N32:N33) -> 69019.524 | O34: =SUM(O32:O33) -> 276078.1 | Q34: إجمالي تكلفة الإيرادات | R34: =SUM(R32:R33) -> 70399.914 | S34: =SUM(S32:S33) -> 70399.914 | T34: =SUM(T32:T33) -> 70399.914 | U34: =SUM(U32:U33) -> 70399.914 | V34: =SUM(V32:V33) -> 281599.66 | X34: إجمالي تكلفة الإيرادات | Y34: =SUM(Y32:Y33) -> 71807.913 | Z34: =SUM(Z32:Z33) -> 71807.913 | AA34: =SUM(AA32:AA33) -> 71807.913 | AB34: =SUM(AB32:AB33) -> 71807.913 | AC34: =SUM(AC32:AC33) -> 287231.65 | AE34: إجمالي تكلفة الإيرادات | AF34: =SUM(AF32:AF33) -> 73244.071 | AG34: =SUM(AG32:AG33) -> 73244.071 | AH34: =SUM(AH32:AH33) -> 73244.071 | AI34: =SUM(AI32:AI33) -> 73244.071 | AJ34: =SUM(AJ32:AJ33) -> 292976.28
C35: مجمل الربح | D35: =D30-D34 -> 205033.8 | E35: =E30-E34 -> #VALUE! | F35: =F30-F34 -> 182233.8 | G35: =G30-G34 -> 124033.8 | H35: =H30-H34 -> #VALUE! | J35: مجمل الربح | K35: =K30-K34 -> 222769.48 | L35: =L30-L34 -> #VALUE! | M35: =M30-M34 -> 198373.48 | N35: =N30-N34 -> 136099.48 | O35: =O30-O34 -> #VALUE! | Q35: مجمل الربح | R35: =R30-R34 -> 241814.32 | S35: =S30-S34 -> #VALUE! | T35: =T30-T34 -> 215710.6 | U35: =U30-U34 -> 149077.42 | V35: =V30-V34 -> #VALUE! | X35: مجمل الربح | Y35: =Y30-Y34 -> 262261.31 | Z35: =Z30-Z34 -> #VALUE! | AA35: =AA30-AA34 -> 234330.33 | AB35: =AB30-AB34 -> 163032.83 | AC35: =AC30-AC34 -> #VALUE! | AE35: مجمل الربح | AF35: =AF30-AF34 -> 284210 | AG35: =AG30-AG34 -> #VALUE! | AH35: =AH30-AH34 -> 254323.85 | AI35: =AI30-AI34 -> 178035.52 | AJ35: =AJ30-AJ34 -> #VALUE!
C36: يطرح المصاريف الأخرى الثابتة | J36: يطرح المصاريف الأخرى الثابتة | Q36: يطرح المصاريف الأخرى الثابتة | X36: يطرح المصاريف الأخرى الثابتة | AE36: يطرح المصاريف الأخرى الثابتة
C37: رواتب الإداريين | D37: =SUM('الدراسة الفنية '!G6,'الدراسة الفنية '!G10) -> 24000 | E37: =SUM('الدراسة الفنية '!G14,'الدراسة الفنية '!G18) -> 42000 | F37: =SUM('الدراسة الفنية '!G22,'الدراسة الفنية '!G26) -> 24000 | G37: =SUM('الدراسة الفنية '!G30,'الدراسة الفنية '!G34) -> 24000 | H37: =SUM(D37:G37) -> 114000 | J37: رواتب الإداريين | K37: =SUM('الدراسة الفنية '!G6,'الدراسة الفنية '!G10)*(1+'الدراسة المالية'!D5) -> 24480 | L37: =E37*1.02 -> 42840 | M37: =F37*1.02 -> 24480 | N37: =G37*1.02 -> 24480 | O37: =SUM(K37:N37) -> 116280 | Q37: رواتب الإداريين | R37: =K37*1.02 -> 24969.6 | S37: =L37*1.02 -> 43696.8 | T37: =M37*1.02 -> 24969.6 | U37: =N37*1.02 -> 24969.6 | V37: =SUM(R37:U37) -> 118605.6 | X37: رواتب الإداريين | Y37: =R37*1.02 -> 25468.992 | Z37: =S37*1.02 -> 44570.736 | AA37: =T37*1.02 -> 25468.992 | AB37: =U37*1.02 -> 25468.992 | AC37: =SUM(Y37:AB37) -> 120977.71 | AE37: رواتب الإداريين | AF37: =Y37*1.02 -> 25978.372 | AG37: =Z37*1.02 -> 45462.151 | AH37: =AA37*1.02 -> 25978.372 | AI37: =AB37*1.02 -> 25978.372 | AJ37: =SUM(AF37:AI37) -> 123397.27
C38: المصاريف التشغيلية الثابتة | D38: ='الدراسة الفنية '!$J137/4 -> 19075.32 | E38: ='الدراسة الفنية '!$J137/4 -> 19075.32 | F38: ='الدراسة الفنية '!$J137/4 -> 19075.32 | G38: ='الدراسة الفنية '!$J137/4 -> 19075.32 | H38: =SUM(D38:G38) -> 76301.28 | J38: المصاريف التشغيلية الثابتة | K38: =D38*1.02 -> 19456.826 | L38: =E38*1.02 -> 19456.826 | M38: =F38*1.02 -> 19456.826 | N38: =G38*1.02 -> 19456.826 | O38: =SUM(K38:N38) -> 77827.306 | Q38: المصاريف التشغيلية الثابتة | R38: =K38*1.02 -> 19845.963 | S38: =L38*1.02 -> 19845.963 | T38: =M38*1.02 -> 19845.963 | U38: =N38*1.02 -> 19845.963 | V38: =SUM(R38:U38) -> 79383.852 | X38: المصاريف التشغيلية الثابتة | Y38: =R38*1.02 -> 20242.882 | Z38: =S38*1.02 -> 20242.882 | AA38: =T38*1.02 -> 20242.882 | AB38: =U38*1.02 -> 20242.882 | AC38: =SUM(Y38:AB38) -> 80971.529 | AE38: المصاريف التشغيلية الثابتة | AF38: =Y38*1.02 -> 20647.74 | AG38: =Z38*1.02 -> 20647.74 | AH38: =AA38*1.02 -> 20647.74 | AI38: =AB38*1.02 -> 20647.74 | AJ38: =SUM(AF38:AI38) -> 82590.959
C39: مصاريف الاستهلاك | D39: ='الدراسة الفنية '!R95 -> 0 | E39: ='الدراسة الفنية '!R73 -> 0 | F39: ='الدراسة الفنية '!R117 -> 0 | G39: ='الدراسة الفنية '!R152 -> 0 | H39: =SUM(D39:G39) -> 0 | J39: مصاريف الاستهلاك | K39: =D39 -> 0 | L39: =E39 -> 0 | M39: =F39 -> 0 | N39: =G39 -> 0 | O39: =SUM(K39:N39) -> 0 | Q39: مصاريف الاستهلاك | R39: =K39 -> 0 | S39: =L39 -> 0 | T39: =M39 -> 0 | U39: =N39 -> 0 | V39: =SUM(R39:U39) -> 0 | X39: مصاريف الاستهلاك | Y39: =R39 -> 0 | Z39: =S39 -> 0 | AA39: =T39 -> 0 | AB39: =U39 -> 0 | AC39: =SUM(Y39:AB39) -> 0 | AE39: مصاريف الاستهلاك | AF39: =Y39 -> 0 | AG39: =Z39 -> 0 | AH39: =AA39 -> 0 | AI39: =AB39 -> 0 | AJ39: =SUM(AF39:AI39) -> 0
C40: مصاريف الصيانة | D40: ='الدراسة الفنية '!R96 -> 0 | E40: ='الدراسة الفنية '!R74 -> 0 | F40: ='الدراسة الفنية '!R118 -> 0 | G40: ='الدراسة الفنية '!R153 -> 0 | H40: =SUM(D40:G40) -> 0 | J40: مصاريف الصيانة | K40: =D40 -> 0 | L40: =E40 -> 0 | M40: =F40 -> 0 | N40: =G40 -> 0 | O40: =SUM(K40:N40) -> 0 | Q40: مصاريف الصيانة | R40: =K40 -> 0 | S40: =L40 -> 0 | T40: =M40 -> 0 | U40: =N40 -> 0 | V40: =SUM(R40:U40) -> 0 | X40: مصاريف الصيانة | Y40: =R40 -> 0 | Z40: =S40 -> 0 | AA40: =T40 -> 0 | AB40: =U40 -> 0 | AC40: =SUM(Y40:AB40) -> 0 | AE40: مصاريف الصيانة | AF40: =Y40 -> 0 | AG40: =Z40 -> 0 | AH40: =AA40 -> 0 | AI40: =AB40 -> 0 | AJ40: =SUM(AF40:AI40) -> 0
C41: المصاريف القانونية | D41: =(#REF!/2)/4 -> #REF! | E41: =(#REF!/2)/4 -> #REF! | F41: =(#REF!/2)/4 -> #REF! | G41: =(#REF!/2)/4 -> #REF! | H41: =SUM(D41:G41) -> #REF! | J41: المصاريف القانونية | K41: =(#REF!/2)/4 -> #REF! | L41: =(#REF!/2)/4 -> #REF! | M41: =(#REF!/2)/4 -> #REF! | N41: =(#REF!/2)/4 -> #REF! | O41: =SUM(K41:N41) -> #REF! | Q41: مصاريف الايجار | R41: ='الدراسة الفنية '!$H144 -> 54000 | S41: ='الدراسة الفنية '!$H145 -> 19200 | T41: ='الدراسة الفنية '!$H146 -> 25000 | U41: ='الدراسة الفنية '!$H147 -> 34300 | V41: =SUM(R41:U41) -> 132500 | X41: مصاريف الايجار | Y41: ='الدراسة الفنية '!$H144 -> 54000 | Z41: ='الدراسة الفنية '!$H145 -> 19200 | AA41: ='الدراسة الفنية '!$H146 -> 25000 | AB41: ='الدراسة الفنية '!$H147 -> 34300 | AC41: =SUM(Y41:AB41) -> 132500 | AE41: مصاريف الايجار | AF41: =Y41 -> 54000 | AG41: =Z41 -> 19200 | AH41: =AA41 -> 25000 | AI41: =AB41 -> 34300 | AJ41: =SUM(AF41:AI41) -> 132500
C42: مصاريف الحملة التسويقية | D42: =#REF!/2/4 -> #REF! | E42: =#REF!/2/4 -> #REF! | F42: =#REF!/2/4 -> #REF! | G42: =#REF!/2/4 -> #REF! | H42: =SUM(D42:G42) -> #REF! | J42: مصاريف الحملة التسويقية | K42: =#REF!/2/4 -> #REF! | L42: =#REF!/2/4 -> #REF! | M42: =#REF!/2/4 -> #REF! | N42: =#REF!/2/4 -> #REF! | O42: =SUM(K42:N42) -> #REF! | Q42: 0 | V42: =SUM(R42:U42) -> 0 | X42: 0 | AC42: =SUM(Y42:AB42) -> 0 | AE42: 0 | AJ42: =SUM(AF42:AI42) -> 0
C43: إجمالي المصاريف الأخرى الثابتة | D43: =SUM(D37:D42) -> #REF! | E43: =SUM(E37:E42) -> #REF! | F43: =SUM(F37:F42) -> #REF! | G43: =SUM(G37:G42) -> #REF! | H43: =SUM(H37:H42) -> #REF! | J43: إجمالي المصاريف الأخرى الثابتة | K43: =SUM(K37:K42) -> #REF! | L43: =SUM(L37:L42) -> #REF! | M43: =SUM(M37:M42) -> #REF! | N43: =SUM(N37:N42) -> #REF! | O43: =SUM(O37:O42) -> #REF! | Q43: إجمالي المصاريف الأخرى الثابتة | R43: =SUM(R37:R42) -> 98815.563 | S43: =SUM(S37:S42) -> 82742.763 | T43: =SUM(T37:T42) -> 69815.563 | U43: =SUM(U37:U42) -> 79115.563 | V43: =SUM(V37:V42) -> 330489.45 | X43: إجمالي المصاريف الأخرى الثابتة | Y43: =SUM(Y37:Y42) -> 99711.874 | Z43: =SUM(Z37:Z42) -> 84013.618 | AA43: =SUM(AA37:AA42) -> 70711.874 | AB43: =SUM(AB37:AB42) -> 80011.874 | AC43: =SUM(AC37:AC42) -> 334449.24 | AE43: إجمالي المصاريف الأخرى الثابتة | AF43: =SUM(AF37:AF42) -> 100626.11 | AG43: =SUM(AG37:AG42) -> 85309.891 | AH43: =SUM(AH37:AH42) -> 71626.112 | AI43: =SUM(AI37:AI42) -> 80926.112 | AJ43: =SUM(AJ37:AJ42) -> 338488.23
C44: صافي الأرباح قبل الضريبة | D44: =D35-D43 -> #REF! | E44: =E35-E43 -> #VALUE! | F44: =F35-F43 -> #REF! | G44: =G35-G43 -> #REF! | H44: =H35-H43 -> #VALUE! | J44: صافي الأرباح قبل الضريبة | K44: =K35-K43 -> #REF! | L44: =L35-L43 -> #VALUE! | M44: =M35-M43 -> #REF! | N44: =N35-N43 -> #REF! | O44: =O35-O43 -> #VALUE! | Q44: صافي الأرباح قبل الضريبة | R44: =R35-R43 -> 142998.75 | S44: =S35-S43 -> #VALUE! | T44: =T35-T43 -> 145895.03 | U44: =U35-U43 -> 69961.853 | V44: =V35-V43 -> #VALUE! | X44: صافي الأرباح قبل الضريبة | Y44: =Y35-Y43 -> 162549.44 | Z44: =Z35-Z43 -> #VALUE! | AA44: =AA35-AA43 -> 163618.46 | AB44: =AB35-AB43 -> 83020.956 | AC44: =AC35-AC43 -> #VALUE! | AE44: صافي الأرباح قبل الضريبة | AF44: =AF35-AF43 -> 183583.89 | AG44: =AG35-AG43 -> #VALUE! | AH44: =AH35-AH43 -> 182697.74 | AI44: =AI35-AI43 -> 97109.412 | AJ44: =AJ35-AJ43 -> #VALUE!
C45: مصروف الضريبة | D45: =D44*'الدراسة المالية'!$D6 -> #REF! | E45: =E44*'الدراسة المالية'!$D6 -> #VALUE! | F45: =F44*'الدراسة المالية'!$D6 -> #REF! | G45: =G44*'الدراسة المالية'!$D6 -> #REF! | H45: =SUM(D45:G45) -> #REF! | J45: مصروف الضريبة | K45: =K44*'الدراسة المالية'!$D6 -> #REF! | L45: =L44*'الدراسة المالية'!$D6 -> #VALUE! | M45: =M44*'الدراسة المالية'!$D6 -> #REF! | N45: =N44*'الدراسة المالية'!$D6 -> #REF! | O45: =SUM(K45:N45) -> #REF! | Q45: مصروف الضريبة | R45: =R44*'الدراسة المالية'!$D6 -> 21449.813 | S45: =S44*'الدراسة المالية'!$D6 -> #VALUE! | T45: =T44*'الدراسة المالية'!$D6 -> 21884.255 | U45: =U44*'الدراسة المالية'!$D6 -> 10494.278 | V45: =SUM(R45:U45) -> #VALUE! | X45: مصروف الضريبة | Y45: =Y44*'الدراسة المالية'!$D6 -> 24382.416 | Z45: =Z44*'الدراسة المالية'!$D6 -> #VALUE! | AA45: =AA44*'الدراسة المالية'!$D6 -> 24542.769 | AB45: =AB44*'الدراسة المالية'!$D6 -> 12453.143 | AC45: =SUM(Y45:AB45) -> #VALUE! | AE45: مصروف الضريبة | AF45: =AF44*'الدراسة المالية'!$D6 -> 27537.583 | AG45: =AG44*'الدراسة المالية'!$D6 -> #VALUE! | AH45: =AH44*'الدراسة المالية'!$D6 -> 27404.661 | AI45: =AI44*'الدراسة المالية'!$D6 -> 14566.412 | AJ45: =SUM(AF45:AI45) -> #VALUE!
C46: صافي الأرباح النهائية | D46: =D44-D45 -> #REF! | E46: =E44-E45 -> #VALUE! | F46: =F44-F45 -> #REF! | G46: =G44-G45 -> #REF! | H46: =H44-H45 -> #VALUE! | J46: صافي الأرباح النهائية | K46: =K44-K45 -> #REF! | L46: =L44-L45 -> #VALUE! | M46: =M44-M45 -> #REF! | N46: =N44-N45 -> #REF! | O46: =O44-O45 -> #VALUE! | Q46: صافي الأرباح النهائية | R46: =R44-R45 -> 121548.94 | S46: =S44-S45 -> #VALUE! | T46: =T44-T45 -> 124010.78 | U46: =U44-U45 -> 59467.575 | V46: =V44-V45 -> #VALUE! | X46: صافي الأرباح النهائية | Y46: =Y44-Y45 -> 138167.02 | Z46: =Z44-Z45 -> #VALUE! | AA46: =AA44-AA45 -> 139075.69 | AB46: =AB44-AB45 -> 70567.813 | AC46: =AC44-AC45 -> #VALUE! | AE46: صافي الأرباح النهائية | AF46: =AF44-AF45 -> 156046.31 | AG46: =AG44-AG45 -> #VALUE! | AH46: =AH44-AH45 -> 155293.08 | AI46: =AI44-AI45 -> 82543.001 | AJ46: =AJ44-AJ45 -> #VALUE!
D48: =D28 -> المسبح | E48: =E28 -> البادل | F48: =F28 -> الملعب متعدد الأغراض | G48: =G28 -> الصالة الرياضية
C49: ='تحليل التعادل '!D9 -> الإيرادات | D49: =D29 -> 272700 | E49: =E29 -> #VALUE! | F49: =F29 -> 249900 | G49: =G29 -> 191700
C50: ='تحليل التعادل '!D10 -> التكاليف المتغيرة | D50: =D34 -> 67666.2 | E50: =E34 -> 67666.2 | F50: =F34 -> 67666.2 | G50: =G34 -> 67666.2
C51: ='تحليل التعادل '!D11 -> التكاليف الثابتة | D51: =D43 -> #REF! | E51: =E43 -> #REF! | F51: =F43 -> #REF! | G51: =G43 -> #REF!
C52: ='تحليل التعادل '!D12 -> نسبة هامش المساهمة | D52: =100%-(D50/D49) -> 0.75186579 | E52: =100%-(E50/E49) -> #VALUE! | F52: =100%-(F50/F49) -> 0.72922689 | G52: =100%-(G50/G49) -> 0.64702034
C53: ='تحليل التعادل '!D13 -> نقطة التعادل بالقيمة | D53: =D51/D52 -> #REF! | E53: =E51/E52 -> #REF! | F53: =F51/F52 -> #REF! | G53: =G51/G52 -> #REF!

Sheet مؤشرات التقييم المسبح
B2: معدل الخصم | E2: ='الدراسة المالية'!D7 -> 0.05
B4: السنوات | D4: صافي الربح | E4: يضاف الاستهلاك | F4: صافي التدفقات النقدية | H4: القيمة الحالية للتدفقات النقدية
A5: 0 | B5: 0 | F5: =-'الدراسة المالية'!G27 -> #REF! | G5: =F5 -> #REF! | H5: =F5 -> #REF!
A6: 1 | B6: السنة 1 | D6: ='قائمة الدخل التقديرية'!D46 -> #REF! | E6: ='قائمة الدخل التقديرية'!D$39 -> 0 | F6: =E6+D6 -> #REF! | G6: =G5+F6 -> #REF! | H6: =(F6*(1/((1+E$2)^A6))) -> #REF!
A7: 2 | B7: السنة 2 | D7: ='قائمة الدخل التقديرية'!K46 -> #REF! | E7: ='قائمة الدخل التقديرية'!D$39 -> 0 | F7: =E7+D7 -> #REF! | G7: =G6+F7 -> #REF! | H7: =(F7*(1/((1+E$2)^A7))) -> #REF!
A8: 3 | B8: السنة 3 | D8: ='قائمة الدخل التقديرية'!R46 -> 121548.94 | E8: ='قائمة الدخل التقديرية'!D$39 -> 0 | F8: =E8+D8 -> 121548.94 | G8: =G7+F8 -> #REF! | H8: =(F8*(1/((1+E$2)^A8))) -> 104998.54
A9: 4 | B9: السنة 4 | D9: ='قائمة الدخل التقديرية'!Y46 -> 138167.02 | E9: ='قائمة الدخل التقديرية'!D$39 -> 0 | F9: =E9+D9 -> 138167.02 | G9: =G8+F9 -> #REF! | H9: =(F9*(1/((1+E$2)^A9))) -> 113670.35
A10: 5 | B10: السنة 5 | D10: ='قائمة الدخل التقديرية'!AF46 -> 156046.31 | E10: ='قائمة الدخل التقديرية'!D$39 -> 0 | F10: =E10+D10 -> 156046.31 | G10: =G9+F10 -> #REF! | H10: =(F10*(1/((1+E$2)^A10))) -> 122266.36
E11: صافي القيمة الحالية NPV | H11: =H5+NPV(E2,F6:F10) -> #REF!
E12: معدل العائد الداخلي IRR | H12: =IRR(F5:F10) -> #VALUE!
E13: فترة الاسترداد Payback | H13: =LOOKUP(0,G5:G10,(A5:A10)-(G5:G10/(F6:F10))) -> #N/A
D14: فترة الاسترداد
D16: # | E16: التدفقات النقدية الخارجة | F16: التدفقات النقدية الداخلة
D17: 0 | E17: =-F5 -> #REF! | F17: 0
D18: 1 | E18: =E17 -> #REF! | F18: =F6 -> #REF!
D19: 2 | E19: =E18 -> #REF! | F19: =F18+F7 -> #REF!
D20: 3 | E20: =E19 -> #REF! | F20: =F19+F8 -> #REF!
D21: 4 | E21: =E20 -> #REF! | F21: =F20+F9 -> #REF!
D22: 5 | E22: =E21 -> #REF! | F22: =F21+F10 -> #REF!

Sheet مؤشرات التقييم البادل
B2: معدل الخصم | E2: ='الدراسة المالية'!D7 -> 0.05
B4: السنوات | D4: صافي الربح | E4: يضاف الاستهلاك | F4: صافي التدفقات النقدية | H4: القيمة الحالية للتدفقات النقدية
A5: 0 | B5: 0 | F5: =-'الدراسة المالية'!H27 -> #REF! | G5: =F5 -> #REF! | H5: =F5 -> #REF!
A6: 1 | B6: السنة 1 | D6: ='قائمة الدخل التقديرية'!E46 -> #VALUE! | E6: ='قائمة الدخل التقديرية'!E$39 -> 0 | F6: =E6+D6 -> #VALUE! | G6: =G5+F6 -> #REF! | H6: =(F6*(1/((1+E$2)^A6))) -> #VALUE!
A7: 2 | B7: السنة 2 | D7: ='قائمة الدخل التقديرية'!L46 -> #VALUE! | E7: ='قائمة الدخل التقديرية'!E$39 -> 0 | F7: =E7+D7 -> #VALUE! | G7: =G6+F7 -> #REF! | H7: =(F7*(1/((1+E$2)^A7))) -> #VALUE!
A8: 3 | B8: السنة 3 | D8: ='قائمة الدخل التقديرية'!S46 -> #VALUE! | E8: ='قائمة الدخل التقديرية'!E$39 -> 0 | F8: =E8+D8 -> #VALUE! | G8: =G7+F8 -> #REF! | H8: =(F8*(1/((1+E$2)^A8))) -> #VALUE!
A9: 4 | B9: السنة 4 | D9: ='قائمة الدخل التقديرية'!Z46 -> #VALUE! | E9: ='قائمة الدخل التقديرية'!E$39 -> 0 | F9: =E9+D9 -> #VALUE! | G9: =G8+F9 -> #REF! | H9: =(F9*(1/((1+E$2)^A9))) -> #VALUE!
A10: 5 | B10: السنة 5 | D10: ='قائمة الدخل التقديرية'!AG46 -> #VALUE! | E10: ='قائمة الدخل التقديرية'!E$39 -> 0 | F10: =E10+D10 -> #VALUE! | G10: =G9+F10 -> #REF! | H10: =(F10*(1/((1+E$2)^A10))) -> #VALUE!
E11: صافي القيمة الحالية NPV | H11: =H5+NPV(E2,F6:F10) -> #REF!
E12: معدل العائد الداخلي IRR | H12: =IRR(F5:F10) -> #VALUE!
E13: فترة الاسترداد Payback | H13: {=LOOKUP(0,G5:G10,(A5:A10)-(G5:G10/(F6:F10)))} -> #N/A
D14: فترة الاسترداد
D16: # | E16: التدفقات النقدية الخارجة | F16: التدفقات النقدية الداخلة
D17: 0 | E17: =-F5 -> #REF! | F17: 0
D18: 1 | E18: =E17 -> #REF! | F18: =F6 -> #VALUE!
D19: 2 | E19: =E18 -> #REF! | F19: =F18+F7 -> #VALUE!
D20: 3 | E20: =E19 -> #REF! | F20: =F19+F8 -> #VALUE!
D21: 4 | E21: =E20 -> #REF! | F21: =F20+F9 -> #VALUE!
D22: 5 | E22: =E21 -> #REF! | F22: =F21+F10 -> #VALUE!

Sheet مؤشرات التقييم الملعب
B2: معدل الخصم | E2: ='الدراسة المالية'!D7 -> 0.05
B4: السنوات | D4: صافي الربح | E4: يضاف الاستهلاك | F4: صافي التدفقات النقدية | H4: القيمة الحالية للتدفقات النقدية
A5: 0 | B5: 0 | F5: =-'الدراسة المالية'!I27 -> #REF! | G5: =F5 -> #REF! | H5: =F5 -> #REF!
A6: 1 | B6: السنة 1 | D6: ='قائمة الدخل التقديرية'!F46 -> #REF! | E6: ='قائمة الدخل التقديرية'!F$39 -> 0 | F6: =E6+D6 -> #REF! | G6: =G5+F6 -> #REF! | H6: =(F6*(1/((1+E$2)^A6))) -> #REF!
A7: 2 | B7: السنة 2 | D7: ='قائمة الدخل التقديرية'!M46 -> #REF! | E7: ='قائمة الدخل التقديرية'!F$39 -> 0 | F7: =E7+D7 -> #REF! | G7: =G6+F7 -> #REF! | H7: =(F7*(1/((1+E$2)^A7))) -> #REF!
A8: 3 | B8: السنة 3 | D8: ='قائمة الدخل التقديرية'!T46 -> 124010.78 | E8: ='قائمة الدخل التقديرية'!F$39 -> 0 | F8: =E8+D8 -> 124010.78 | G8: =G7+F8 -> #REF! | H8: =(F8*(1/((1+E$2)^A8))) -> 107125.17
A9: 4 | B9: السنة 4 | D9: ='قائمة الدخل التقديرية'!AA46 -> 139075.69 | E9: ='قائمة الدخل التقديرية'!F$39 -> 0 | F9: =E9+D9 -> 139075.69 | G9: =G8+F9 -> #REF! | H9: =(F9*(1/((1+E$2)^A9))) -> 114417.91
A10: 5 | B10: السنة 5 | D10: ='قائمة الدخل التقديرية'!AH46 -> 155293.08 | E10: ='قائمة الدخل التقديرية'!F$39 -> 0 | F10: =E10+D10 -> 155293.08 | G10: =G9+F10 -> #REF! | H10: =(F10*(1/((1+E$2)^A10))) -> 121676.19
E11: صافي القيمة الحالية NPV | H11: =H5+NPV(E2,F6:F10) -> #REF!
E12: معدل العائد الداخلي IRR | H12: =IRR(F5:F10) -> #VALUE!
E13: فترة الاسترداد Payback | H13: =LOOKUP(0,G5:G10,(A5:A10)-(G5:G10/(F6:F10))) -> #N/A
D14: فترة الاسترداد
D16: # | E16: التدفقات النقدية الخارجة | F16: التدفقات النقدية الداخلة
D17: 0 | E17: =-F5 -> #REF! | F17: 0
D18: 1 | E18: =E17 -> #REF! | F18: =F6 -> #REF!
D19: 2 | E19: =E18 -> #REF! | F19: =F18+F7 -> #REF!
D20: 3 | E20: =E19 -> #REF! | F20: =F19+F8 -> #REF!
D21: 4 | E21: =E20 -> #REF! | F21: =F20+F9 -> #REF!
D22: 5 | E22: =E21 -> #REF! | F22: =F21+F10 -> #REF!

Sheet مؤشرات التقييم الصالة الرياضية
B2: معدل الخصم | E2: ='الدراسة المالية'!D7 -> 0.05
B4: السنوات | D4: صافي الربح | E4: يضاف الاستهلاك | F4: صافي التدفقات النقدية | H4: القيمة الحالية للتدفقات النقدية
A5: 0 | B5: 0 | F5: =-'الدراسة المالية'!J27 -> #REF! | G5: =F5 -> #REF! | H5: =F5 -> #REF!
A6: 1 | B6: السنة 1 | D6: ='قائمة الدخل التقديرية'!G46 -> #REF! | E6: ='قائمة الدخل التقديرية'!G$39 -> 0 | F6: =E6+D6 -> #REF! | G6: =G5+F6 -> #REF! | H6: =(F6*(1/((1+E$2)^A6))) -> #REF!
A7: 2 | B7: السنة 2 | D7: ='قائمة الدخل التقديرية'!N46 -> #REF! | E7: ='قائمة الدخل التقديرية'!G$39 -> 0 | F7: =E7+D7 -> #REF! | G7: =G6+F7 -> #REF! | H7: =(F7*(1/((1+E$2)^A7))) -> #REF!
A8: 3 | B8: السنة 3 | D8: ='قائمة الدخل التقديرية'!U46 -> 59467.575 | E8: ='قائمة الدخل التقديرية'!G$39 -> 0 | F8: =E8+D8 -> 59467.575 | G8: =G7+F8 -> #REF! | H8: =(F8*(1/((1+E$2)^A8))) -> 51370.327
A9: 4 | B9: السنة 4 | D9: ='قائمة الدخل التقديرية'!AB46 -> 70567.813 | E9: ='قائمة الدخل التقديرية'!G$39 -> 0 | F9: =E9+D9 -> 70567.813 | G9: =G8+F9 -> #REF! | H9: =(F9*(1/((1+E$2)^A9))) -> 58056.314
A10: 5 | B10: السنة 5 | D10: ='قائمة الدخل التقديرية'!AI46 -> 82543.001 | E10: ='قائمة الدخل التقديرية'!G$39 -> 0 | F10: =E10+D10 -> 82543.001 | G10: =G9+F10 -> #REF! | H10: =(F10*(1/((1+E$2)^A10))) -> 64674.601
E11: صافي القيمة الحالية NPV | H11: =H5+NPV(E2,F6:F10) -> #REF!
E12: معدل العائد الداخلي IRR | H12: =IRR(F5:F10) -> #VALUE!
E13: فترة الاسترداد Payback | H13: =LOOKUP(0,G5:G10,(A5:A10)-(G5:G10/(F6:F10))) -> #N/A
D14: فترة الاسترداد
D16: # | E16: التدفقات النقدية الخارجة | F16: التدفقات النقدية الداخلة
D17: 0 | E17: =-F5 -> #REF! | F17: 0
D18: 1 | E18: =E17 -> #REF! | F18: =F6 -> #REF!
D19: 2 | E19: =E18 -> #REF! | F19: =F18+F7 -> #REF!
D20: 3 | E20: =E19 -> #REF! | F20: =F19+F8 -> #REF!
D21: 4 | E21: =E20 -> #REF! | F21: =F20+F9 -> #REF!
D22: 5 | E22: =E21 -> #REF! | F22: =F21+F10 -> #REF!

Sheet فترة الاسترداد
B3: فترة الاسترداد
B6: # | C6: التدفقات النقدية الخارجة | D6: التدفقات النقدية الداخلة
B7: 0 | C7: ='الدراسة المالية'!G17 -> #REF! | D7: 0
B8: 1 | C8: =C7 -> #REF! | D8: ='مؤشرات تقييم المشروع '!F6 -> #VALUE!
B9: 2 | C9: =C8 -> #REF! | D9: =D8+'مؤشرات تقييم المشروع '!F7 -> #VALUE!
B10: 3 | C10: =C9 -> #REF! | D10: =D9+'مؤشرات تقييم المشروع '!F8 -> #VALUE!
B11: 4 | C11: =C10 -> #REF! | D11: =D10+'مؤشرات تقييم المشروع '!F9 -> #VALUE!
B12: 5 | C12: =C11 -> #REF! | D12: =D11+'مؤشرات تقييم المشروع '!F10 -> #VALUE!

Sheet مؤشرات تقييم المشروع 
B2: معدل الخصم | E2: ='الدراسة المالية'!D7 -> 0.05
B4: السنوات | D4: صافي الربح | E4: يضاف الاستهلاك | F4: صافي التدفقات النقدية | H4: القيمة الحالية للتدفقات النقدية
A5: 0 | B5: 0 | F5: =-'الدراسة المالية'!G17 -> #REF! | G5: =F5 -> #REF! | H5: =F5 -> #REF!
A6: 1 | B6: السنة 1 | D6: ='قائمة الدخل التقديرية'!D23 -> #VALUE! | E6: ='قائمة الدخل التقديرية'!D15 -> 14751613 | F6: =E6+D6 -> #VALUE! | G6: =G5+F6 -> #REF! | H6: =(F6*(1/((1+E$2)^A6))) -> #VALUE!
A7: 2 | B7: السنة 2 | D7: ='قائمة الدخل التقديرية'!E23 -> #VALUE! | E7: ='قائمة الدخل التقديرية'!E15 -> 14751613 | F7: =E7+D7 -> #VALUE! | G7: =G6+F7 -> #REF! | H7: =(F7*(1/((1+E$2)^A7))) -> #VALUE!
A8: 3 | B8: السنة 3 | D8: ='قائمة الدخل التقديرية'!F23 -> #VALUE! | E8: ='قائمة الدخل التقديرية'!F15 -> 14751613 | F8: =E8+D8 -> #VALUE! | G8: =G7+F8 -> #REF! | H8: =(F8*(1/((1+E$2)^A8))) -> #VALUE!
A9: 4 | B9: السنة 4 | D9: ='قائمة الدخل التقديرية'!G23 -> #VALUE! | E9: ='قائمة الدخل التقديرية'!G15 -> 14751613 | F9: =E9+D9 -> #VALUE! | G9: =G8+F9 -> #REF! | H9: =(F9*(1/((1+E$2)^A9))) -> #VALUE!
A10: 5 | B10: السنة 5 | D10: ='قائمة الدخل التقديرية'!H23 -> #VALUE! | E10: ='قائمة الدخل التقديرية'!H15 -> 14751613 | F10: =E10+D10 -> #VALUE! | G10: =G9+F10 -> #REF! | H10: =(F10*(1/((1+E$2)^A10))) -> #VALUE!
E11: صافي القيمة الحالية NPV | H11: =H5+NPV(E2,F6:F10) -> #REF!
E12: معدل العائد الداخلي IRR | H12: =IRR(F5:F10) -> #VALUE!
E13: فترة الاسترداد Payback | H13: =LOOKUP(0,G5:G10,(A5:A10)-(G5:G10/(F6:F10))) -> #N/A

Sheet اسعار الخدمات 
C3: الخدمات المقدمة من ماك بلاش وتوصيفها
B4: # | C4: البند | D4: الوصف | E4: القيمة | F4: لماذا تم اختيار القيمة ؟ | G4: التكلفة | H4: كيف تم احتساب التكلفة ؟ | I4: الربح المتوقع بالريال | J4: الفئة
B5: 1 | C5: البند | D5: الوصف | E5: القيمة (سعر البيع) | F5: لماذا تم اختيار القيمة؟ | G5: التكلفة | H5: كيف تم احتساب التكلفة؟ | I5: الربح المتوقع (ريال) | J5: الأفراد
B6: =1+B5 -> 2 | C6: اشتراكات مميزة (Premium) | D6: مزايا إضافية مثل محتوى حصري وإزالة إعلانات | E6: 30 ريال/شهر | F6: منافس لخدمات عالمية مثل Spotify Gaming | G6: 10 ريال/مستخدم | H6: استضافة + صيانة + دعم فني | I6: 20 ريال/مستخدم
B7: =1+B6 -> 3 | C7: شراء عناصر رقمية | D7: Skins وأدوات وبطاقات داخل الألعاب | E7: 20 – 100 ريال | F7: مشابه لأسعار Fortnite وPUBG | G7: 5 – 20 ريال | H7: رسوم تطوير/ترخيص | I7: 15 – 80 ريال
B8: =1+B7 -> 4 | C8: رسوم بطولات إلكترونية | D8: مشاركة في بطولات بجوائز | E8: 100 ريال/مشارك | F8: سعر متوسط للبطولات المحلية | G8: 40 ريال | H8: تنظيم + جوائز | I8: 60 ريال/مشارك
B9: =1+B8 -> 5 | C9: بطاقات شحن الألعاب | D9: بطاقات بلايستيشن، إكس بوكس، ستيم | E9: 50 – 300 ريال | F9: مطابق لأسعار السوق | G9: 45 – 280 ريال | H9: شراء جملة من الموردين | I9: 5 – 20 ريال
B10: =1+B9 -> 6 | C10: متجر ألعاب رقمي | D10: شراء ألعاب مباشرة عبر المنصة | E10: 100 – 300 ريال | F10: مشابه لـ Steam وEpic | G10: 80 – 250 ريال | H10: تراخيص توزيع الألعاب | I10: 20 – 50 ريال
B11: =1+B10 -> 7 | C11: لعبة الشهر | D11: اشتراك يمنح لعبة كل شهر | E11: 40 ريال/شهر | F11: مثل Xbox Game Pass مصغر | G11: 20 ريال | H11: تراخيص ألعاب | I11: 20 ريال
B12: =1+B11 -> 8 | C12: تأجير حسابات ألعاب | D12: استئجار حسابات لتجربة ألعاب مميزة | E12: 25 ريال/يوم | F12: سعر جذاب للهواة | G12: 10 ريال | H12: صيانة الحساب + تراخيص | I12: 15 ريال
B13: =1+B12 -> 9 | C13: تدريب شخصي (Coaching) | D13: جلسة مع لاعب محترف | E13: 150 ريال/ساعة | F13: سعر قريب من سوق التدريب المحلي | G13: 70 ريال | H13: أتعاب المدرب | I13: 80 ريال
B14: =1+B13 -> 10 | C14: ورش عمل مجتمعية | D14: ورش تعليم صناعة الألعاب أو البث | E14: 200 ريال/ورشة | F14: مقبول كورش قصيرة | G14: 100 ريال | H14: منصة + مدرب | I14: 100 ريال
B15: =1+B14 -> 11 | C15: مسابقات أسبوعية | D15: تحديات بجوائز رمزية | E15: 20 ريال/مشارك | F15: لجذب التفاعل | G15: 10 ريال | H15: جوائز + استضافة | I15: 10 ريال
B16: =1+B15 -> 12 | C16: خدمة إعادة البث (Replay) | D16: حفظ وإعادة لقطات اللعب | E16: 15 ريال/شهر | F16: مشابه لخدمات Twitch Replay | G16: 5 ريال | H16: سيرفر + تخزين | I16: 10 ريال
B17: =1+B16 -> 13 | C17: عضوية عائلية | D17: اشتراك لعدة مستخدمين (Family Pack) | E17: 100 ريال/شهر | F17: مشابه لخدمات Netflix Family | G17: 40 ريال | H17: استضافة + دعم | I17: 60 ريال
... B25: =1+B24 -> 21 | C25: نظام الولاء والنقاط | D25: نقاط تستبدل بمكافآت | E25: 20 ريال/اشتراك | F25: يزيد التفاعل | G25: 5 ريال | H25: تطوير + إدارة | I25: 15 ريال
B26: =1+B25 -> 22 | C26: إدارة الحملات التسويقية | D26: تنظيم حملات المؤثر مع الشركات | E26: 20,000 – 100,000 ريال/حملة | F26: منافس لسوق إدارة المؤثرين | G26: 10,000 – 50,000 ريال | H26: فريق إدارة + إعلانات | I26: 10,000 – 50,000 ريال | J26: للمؤثرين
B27: =1+B26 -> 23 | C27: إنتاج فيديوهات مخصصة | D27: مونتاج فيديوهات ترويجية للبثوص | E27: 5,000 – 15,000 ريال/فيديو | F27: سعر سوقي لإنتاج المحتوى | G27: 3,000 – 7,000 ريال | H27: تصوير + مونتاج | I27: 2,000 – 8,000 ريال
B28: =1+B27 -> 24 | C28: تصميم الهوية البصرية | D28: شعار + بانر + ثيمات للبث | E28: 3,000 – 8,000 ريال | F28: متوافق مع أسعار المصممين | G28: 1,500 – 4,000 ريال | H28: تصميم + مراجعات | I28: 1,500 – 4,000 ريال
B29: =1+B28 -> 25 | C29: استوديو تصوير مؤقت | D29: تأجير استوديو مع معدات | E29: 2,500 – 7,500 ريال/يوم | F29: مثل أسعار استوديوهات جدة/الرياض | G29: 1,000 – 4,000 ريال | H29: تأجير معدات + مساحة | I29: 1,500 – 3,500 ريال
B30: =1+B29 -> 26 | C30: خدمة البث المباشر الاحترافي | D30: إعداد وإدارة بث مباشر | E30: 10,000 – 25,000 ريال/فعالية | F30: مشابه لشركات البث | G30: 5,000 – 12,000 ريال | H30: معدات + تقنيين | I30: 5,000 – 13,000 ريال
B31: =1+B30 -> 27 | C31: إدارة حسابات التواصل | D31: جدولة المحتوى + الردود | E31: 3,000 – 10,000 ريال/شهر | F31: سعر السوق لإدارة الحسابات | G31: 1,500 – 4,000 ريال | H31: مدير حساب + أدوات | I31: 1,500 – 6,000 ريال
B32: =1+B31 -> 28 | C32: تحليلات أداء المحتوى | D32: تقارير أداء وتفاعل الجمهور | E32: 2,000 – 5,000 ريال/تقرير | F32: قيمة عادلة مقابل البيانات | G32: 800 – 2,000 ريال | H32: أدوات تحليل | I32: 1,200 – 3,000 ريال
B33: =1+B32 -> 29 | C33: عقود رعاية وشراكات | D33: صياغة عقود قانونية للمؤثرين | E33: 4,000 – 12,000 ريال/عقد | F33: متوافق مع مكاتب المحاماة | G33: 2,000 – 5,000 ريال | H33: استشارات قانونية | I33: 2,000 – 7,000 ريال
B34: =1+B33 -> 30 | C34: تدريب المؤثرين | D34: ورش تدريب على تحسين البث | E34: 1,500 – 3,000 ريال/ورشة | F34: أسعار دورات تطوير المهارات | G34: 700 – 1,500 ريال | H34: مدرب + منصة | I34: 800 – 1,500 ريال
B35: =1+B34 -> 31 | C35: متجر إلكتروني شخصي | D35: إنشاء متجر لبيع منتجات المؤثر | E35: 8,000 – 20,000 ريال | F35: سعر شبيه بـ Shopify Solutions | G35: 3,000 – 8,000 ريال | H35: تطوير متجر + تصميم | I35: 5,000 – 12,000 ريال
B36: =1+B35 -> 32 | C36: ربط مع شركات رعاية | D36: تقديم المؤثر لشركات مناسبة | E36: 5,000 ريال/صفقة | F36: قيمة بسيطة لتحفيز الرعايات | G36: 1,500 ريال | H36: علاقات + إدارة | I36: 3,500 ريال
B37: =1+B36 -> 33 | C37: خدمة الإنتاج الصوتي | D37: تسجيل وتعليق صوتي احترافي | E37: 1,500 – 4,000 ريال | F37: مطابق لسوق الإنتاج الصوتي | G37: 700 – 1,800 ريال | H37: استوديو + معدات | I37: 800 – 2,200 ريال
B38: =1+B37 -> 34 | C38: إدارة حقوق المحتوى | D38: حماية الفيديوهات من السرقة | E38: 4,000 – 10,000 ريال/شهر | F38: متوافق مع خدمات حماية المحتوى | G38: 2,000 – 4,000 ريال | H38: نظام حماية + متابعة | I38: 2,000 – 6,000 ريال
... B45: =1+B44 -> 41 | C45: On-Demand Merch 2-Hour | D45: متجر مرش سريع بالطباعة عند الطلب خلال ساعتين | E45: 50 – 200 ريال/منتج | F45: منتج فوري يعزز المبيعات | G45: 25 – 80 ريال | H45: طباعة محلية + لوجستيات | I45: 25 – 120 ريال
B46: =1+B45 -> 42 | C46: إعلانات ورعايات داخل المنصة | D46: حجز مساحات إعلانية داخل المنصة أو أثناء البث | E46: 100,000 – 500,000 ريال/حملة | F46: منافس لمنصات مثل Twitch وYouTube Gaming | G46: 50,000 – 150,000 ريال | H46: إنتاج محتوى + إدارة الحملة | I46: 50,000 – 350,000 ريال | J46: لشركات التجارية
B47: =1+B46 -> 43 | C47: رعاية البطولات الإلكترونية | D47: شراكة مع ماك بلاش لرعاية الفعاليات | E47: 150,000 – 600,000 ريال/بطولة | F47: متوافق مع السوق السعودي (Gamers8) | G47: 80,000 – 250,000 ريال | H47: تنظيم البطولة + الجوائز | I47: 70,000 – 350,000 ريال
B48: =1+B47 -> 44 | C48: إنتاج محتوى دعائي للشركات | D48: فيديوهات تسويقية للألعاب أو المنتجات | E48: 30,000 – 80,000 ريال/فيديو | F48: سعر السوق للإنتاج الإعلامي | G48: 15,000 – 40,000 ريال | H48: تصوير + إخراج + مونتاج | I48: 15,000 – 40,000 ريال
B49: =1+B48 -> 45 | C49: منصة إطلاق المنتجات (Product Launch) | D49: بث وإعلان عن منتجات جديدة عبر ماك بلاش | E49: 50,000 – 200,000 ريال | F49: مشابه لسوق الإطلاقات الرقمية | G49: 25,000 – 80,000 ريال | H49: تجهيز منصة + حملات | I49: 25,000 – 120,000 ريال
B50: =1+B49 -> 46 | C50: متجر إلكتروني مخصص | D50: إنشاء متجر للشركات لبيع منتجات ألعاب أو إكسسوارات | E50: 40,000 – 120,000 ريال | F50: أسعار مقاربة لتصميم متاجر Shopify | G50: 20,000 – 50,000 ريال | H50: تطوير + تصميم | I50: 20,000 – 70,000 ريال
B51: =1+B50 -> 47 | C51: استضافة بثوث الشركات | D51: بث فعاليات ومؤتمرات الشركات عبر المنصة | E51: 25,000 – 100,000 ريال/فعالية | F51: أسعار مقاربة لخدمات البث المحترفة | G51: 10,000 – 40,000 ريال | H51: معدات + سيرفرات | I51: 15,000 – 60,000 ريال
B52: =1+B51 -> 48 | C52: تقارير تحليل اللاعبين (Analytics) | D52: تقارير عن سلوك اللاعبين لصالح الشركات | E52: 20,000 – 50,000 ريال/تقرير | F52: قيمة سوقية للبيانات الضخمة | G52: 8,000 – 20,000 ريال | H52: أدوات BI + فريق تحليل | I52: 12,000 – 30,000 ريال
B53: =1+B52 -> 49 | C53: إدارة حملات تسويق رقمية | D53: حملات تسويقية موجهة لجمهور اللاعبين | E53: 30,000 – 150,000 ريال | F53: أسعار مشابهة لشركات التسويق الكبرى | G53: 15,000 – 70,000 ريال | H53: إعلانات ممولة + إدارة | I53: 15,000 – 80,000 ريال
B54: =1+B53 -> 50 | C54: تطوير ألعاب للشركات (Advergames) | D54: ألعاب مصممة خصيصًا للتسويق | E54: 120,000 – 400,000 ريال | F54: أسعار السوق الإقليمي للألعاب التفاعلية | G54: 70,000 – 200,000 ريال | H54: برمجة + تصميم + اختبار | I54: 50,000 – 200,000 ريال
B55: =1+B54 -> 51 | C55: تنظيم فعاليات ألعاب للشركات | D55: فعاليات ترفيهية أو تسويقية عبر الألعاب | E55: 80,000 – 300,000 ريال | F55: متوافق مع السوق السعودي | G55: 40,000 – 120,000 ريال | H55: تنظيم + تجهيز + محتوى | I55: 40,000 – 180,000 ريال
B56: =1+B55 -> 52 | C56: ربط مع المؤثرين | D56: توصيل الشركات بالمؤثرين المناسبين | E56: 20,000 – 80,000 ريال/حملة | F56: نفس أسعار وكالات المؤثرين | G56: 10,000 – 40,000 ريال | H56: أتعاب المؤثرين + إدارة | I56: 10,000 – 40,000 ريال
B57: =1+B56 -> 53 | C57: إنتاج محتوى تفاعلي | D57: اختبارات ومسابقات موجهة لمنتجات الشركات | E57: 15,000 – 50,000 ريال | F57: أسعار مناسبة لحملات تفاعلية | G57: 7,000 – 20,000 ريال | H57: تصميم + تطوير | I57: 8,000 – 30,000 ريال
B58: =1+B57 -> 54 | C58: خدمات تصوير احترافية | D58: تصوير منتجات شركات الألعاب/التقنية | E58: 8,000 – 25,000 ريال/جلسة | F58: أسعار السوق السعودي للتصوير | G58: 4,000 – 12,000 ريال | H58: معدات + فريق تصوير | I58: 4,000 – 13,000 ريال
... B64: =1+B63 -> 60 | C64: Retail-to-Gamer Bridge | D64: ربط عروض المتاجر التقليدية بمكافآت داخل الألعاب | E64: 20,000 – 60,000 ريال | F64: يقيس أثر المبيعات عبر الإنترنت والواقع | G64: 10,000 – 25,000 ريال | H64: تطوير + تكامل API | I64: 10,000 – 35,000 ريال
B65: =1+B64 -> 61 | C65: خدمات استضافة منتجات الشركات | D65: عرض منتجات الشركات داخل المنصة (Marketplace B2B) | E65: 5% عمولة | F65: مشابه لـ Amazon/Ebay | G65: 0.02 | H65: رسوم دفع + إدارة | I65: 3% عمولة
B66: =1+B65 -> 62 | C66: تقارير سوق الألعاب | D66: تقارير تحليلية عن السوق والاتجاهات | E66: 15,000 – 40,000 ريال/تقرير | F66: قيمة تنافسية مقارنة بشركات الأبحاث | G66: 6,000 – 15,000 ريال | H66: فريق بحث + أدوات تحليل | I66: 9,000 – 25,000 ريال | J66: المستثمرين
B67: =1+B66 -> 63 | C67: دراسات جدوى لمشاريع الألعاب | D67: دراسة جدوى لمشاريع استثمارية في الألعاب | E67: 50,000 – 120,000 ريال | F67: أسعار معتادة في مكاتب الاستشارات | G67: 25,000 – 60,000 ريال | H67: محللين ماليين + مستشارين | I67: 25,000 – 60,000 ريال
B68: =1+B67 -> 64 | C68: استشارات استثمارية | D68: جلسات استشارية موجهة للاستثمار في قطاع الألعاب | E68: 5,000 – 15,000 ريال/جلسة | F68: مشابه لأسعار مكاتب استشارية متخصصة | G68: 2,000 – 6,000 ريال | H68: خبراء + إعداد مواد | I68: 3,000 – 9,000 ريال
B69: =1+B68 -> 65 | C69: ندوات خاصة للمستثمرين | D69: فعاليات حصرية لعرض فرص الاستثمار | E69: 30,000 – 100,000 ريال | F69: منافس لسوق الفعاليات الخاصة | G69: 15,000 – 40,000 ريال | H69: قاعة + تجهيزات + محتوى | I69: 15,000 – 60,000 ريال
B70: =1+B69 -> 66 | C70: تقارير ذكاء الأعمال (BI Reports) | D70: تقارير رقمية تفاعلية عن بيانات اللاعبين والسوق | E70: 20,000 – 50,000 ريال | F70: أسعار مشابهة لمكاتب BI | G70: 8,000 – 20,000 ريال | H70: أدوات BI + فريق تحليل | I70: 12,000 – 30,000 ريال
B71: =1+B70 -> 67 | C71: خدمات Due Diligence | D71: تدقيق وفحص شركات ألعاب قبل الاستثمار | E71: 40,000 – 90,000 ريال | F71: أسعار قريبة من مكاتب المحاماة | G71: 20,000 – 45,000 ريال | H71: محامون + محللون ماليون | I71: 20,000 – 45,000 ريال
B72: =1+B71 -> 68 | C72: إدارة صناديق ألعاب صغيرة | D72: إنشاء وإدارة صناديق استثمارية صغيرة للألعاب | E72: 200,000 – 500,000 ريال | F72: منافس للشركات الاستثمارية الناشئة | G72: 120,000 – 250,000 ريال | H72: إدارة + محاسبة + تقنية | I72: 80,000 – 250,000 ريال
B73: =1+B72 -> 69 | C73: خدمة الوصول المبكر للمشاريع | D73: إعطاء المستثمرين حق الوصول لمشاريع جديدة | E73: 25,000 ريال/اشتراك سنوي | F73: قيمة مضافة لجذب المستثمرين | G73: 10,000 ريال | H73: تشغيل + محتوى حصري | I73: 15,000 ريال
B74: =1+B73 -> 70 | C74: تقارير المخاطر | D74: تحليلات حول مخاطر الاستثمار في الألعاب | E74: 12,000 – 30,000 ريال | F74: أسعار قريبة من الاستشارات المالية | G74: 5,000 – 12,000 ريال | H74: فريق قانوني + مالي | I74: 7,000 – 18,000 ريال
B75: =1+B74 -> 71 | C75: خدمة Pitch Deck | D75: إعداد عروض تقديمية لجذب الاستثمار | E75: 15,000 – 35,000 ريال | F75: مشابه لشركات التسويق | G75: 6,000 – 12,000 ريال | H75: تصميم + محتوى | I75: 9,000 – 23,000 ريال
B76: =1+B75 -> 72 | C76: استضافة جلسات Networking | D76: فعاليات ربط بين مستثمرين ومطورين | E76: 20,000 – 60,000 ريال | F76: شبيه بجلسات حاضنات الأعمال | G76: 10,000 – 25,000 ريال | H76: تنظيم + مكان | I76: 10,000 – 35,000 ريال
B77: =1+B76 -> 73 | C77: ورش عمل استثمارية | D77: ورش حول الاستثمار في صناعة الألعاب | E77: 10,000 – 25,000 ريال | F77: أسعار دورات تخصصية | G77: 4,000 – 10,000 ريال | H77: مدربين + تجهيزات | I77: 6,000 – 15,000 ريال
B78: =1+B77 -> 74 | C78: خدمات قانونية استثمارية | D78: عقود استثمار وحماية ملكية فكرية | E78: 30,000 – 70,000 ريال | F78: أسعار مكاتب قانونية كبرى | G78: 15,000 – 30,000 ريال | H78: محامون + مراجعة | I78: 15,000 – 40,000 ريال
... B85: =1+B84 -> 81 | C85: منصة تواصل للمستثمرين | D85: عضوية في شبكة استثمارية خاصة داخل ماك بلاش | E85: 10,000 ريال/سنة | F85: قيمة رمزية لبناء مجتمع مغلق | G85: 4,000 ريال | H85: إدارة + تقنية + محتوى | I85: 6,000 ريال
B86: =1+B85 -> 82 | C86: تنظيم بطولات وطنية للألعاب الإلكترونية | D86: تخطيط وتنفيذ بطولات رسمية تحت إشراف الحكومة | E86: 500,000 – 2,000,000 ريال/بطولة | F86: أسعار بطولات بحجم Gamers8 | G86: 250,000 – 1,000,000 ريال | H86: تنظيم + جوائز + بث | I86: 250,000 – 1,000,000 ريال | J86: الجهات الحكومية والتنظيمية
B87: =1+B86 -> 83 | C87: إعداد تقارير استراتيجية عن صناعة الألعاب | D87: تقارير سياسات وتوصيات للحكومة | E87: 100,000 – 250,000 ريال/تقرير | F87: أسعار مشابهة لمكاتب استشارية كبرى | G87: 40,000 – 100,000 ريال | H87: فريق بحث + محللين | I87: 60,000 – 150,000 ريال
B88: =1+B87 -> 84 | C88: شراكات مجتمعية شبابية | D88: مبادرات ترفيهية وتعليمية للشباب | E88: 200,000 – 600,000 ريال/مبادرة | F88: سعر منطقي لبرامج اجتماعية | G88: 100,000 – 250,000 ريال | H88: فعاليات + حملات | I88: 100,000 – 350,000 ريال
B89: =1+B88 -> 85 | C89: تطوير منصات تدريبية حكومية | D89: منصات لتعليم صناعة الألعاب | E89: 300,000 – 800,000 ريال | F89: مشابه لمشاريع التدريب الرقمي | G89: 150,000 – 400,000 ريال | H89: تطوير + محتوى | I89: 150,000 – 400,000 ريال
B90: =1+B89 -> 86 | C90: ورش عمل للمعلمين والطلاب | D90: تدريب على الألعاب التعليمية | E90: 50,000 – 150,000 ريال/ورشة | F90: منافس لسوق التدريب الرسمي | G90: 20,000 – 70,000 ريال | H90: مدربين + تجهيزات | I90: 30,000 – 80,000 ريال
B91: =1+B90 -> 87 | C91: إدارة فعاليات عامة | D91: تنظيم مهرجانات ومعارض ترفيهية | E91: 400,000 – 1,200,000 ريال | F91: متماشي مع فعاليات هيئة الترفيه | G91: 200,000 – 600,000 ريال | H91: تنظيم + محتوى | I91: 200,000 – 600,000 ريال
B92: =1+B91 -> 88 | C92: حملات توعية رقمية | D92: حملات توعوية باستخدام الألعاب | E92: 100,000 – 300,000 ريال | F92: شبيه بأسعار الحملات الإعلامية الرسمية | G92: 50,000 – 120,000 ريال | H92: محتوى + منصات | I92: 50,000 – 180,000 ريال
B93: =1+B92 -> 89 | C93: إنتاج محتوى وطني للألعاب | D93: فيديوهات عن الهوية الوطنية بالألعاب | E93: 80,000 – 200,000 ريال | F93: منافس لأسعار الإنتاج الإعلامي | G93: 40,000 – 90,000 ريال | H93: تصوير + مونتاج | I93: 40,000 – 110,000 ريال
B94: =1+B93 -> 90 | C94: شراكات مع المدارس والجامعات | D94: ربط التعليم بالألعاب الإلكترونية | E94: 150,000 – 400,000 ريال/برنامج | F94: منطقي لمشاريع حكومية تعليمية | G94: 70,000 – 200,000 ريال | H94: محتوى + تدريب | I94: 80,000 – 200,000 ريال
B95: =1+B94 -> 91 | C95: أنظمة تتبع الأداء | D95: أنظمة قياس أثر الفعاليات الحكومية | E95: 50,000 – 150,000 ريال | F95: أسعار SaaS حكومية | G95: 20,000 – 60,000 ريال | H95: تطوير + تكامل | I95: 30,000 – 90,000 ريال
B96: =1+B95 -> 92 | C96: محتوى ألعاب تعليمية | D96: تطوير ألعاب مرتبطة بالمناهج | E96: 200,000 – 600,000 ريال | F96: قيمة مناسبة لمشاريع تعليمية كبرى | G96: 100,000 – 300,000 ريال | H96: برمجة + تصميم | I96: 100,000 – 300,000 ريال
B97: =1+B96 -> 93 | C97: منصات حكومية للبث | D97: بث مباشر للفعاليات الوطنية | E97: 150,000 – 400,000 ريال | F97: منافس لسوق البث الرسمي | G97: 70,000 – 200,000 ريال | H97: سيرفرات + فريق تقني | I97: 80,000 – 200,000 ريال
B98: =1+B97 -> 94 | C98: استضافة معارض دولية | D98: تنظيم مشاركة سعودية في معارض مثل E3 | E98: 800,000 – 3,000,000 ريال | F98: أسعار مشاركة حكومية خارجية | G98: 400,000 – 1,500,000 ريال | H98: تنظيم + سفر + تجهيز | I98: 400,000 – 1,500,000 ريال
... B105: =1+B104 -> 101 | C105: محتوى إحصائي دوري | D105: نشر تقارير دورية عن اللاعبين | E105: 60,000 – 120,000 ريال/تقرير | F105: سعر مناسب لتقارير بحثية رسمية | G105: 25,000 – 50,000 ريال | H105: أدوات BI + محللين | I105: 35,000 – 70,000 ريال
B106: =1+B105 -> 102 | C106: تطوير ألعاب تعليمية | D106: برمجة ألعاب تربط المناهج الدراسية بالتفاعل | E106: 150,000 – 400,000 ريال | F106: منافس لسوق الـ Serious Games | G106: 80,000 – 200,000 ريال | H106: برمجة + تصميم + اختبار | I106: 70,000 – 200,000 ريال | J106: المؤسسات التعليمية والثقافية
B107: =1+B106 -> 103 | C107: منصات تدريب على صناعة الألعاب | D107: تطوير منصات تدريبية تفاعلية | E107: 200,000 – 500,000 ريال | F107: مشابه لبرامج الجامعات التقنية | G107: 100,000 – 250,000 ريال | H107: تطوير + محتوى | I107: 100,000 – 250,000 ريال
B108: =1+B107 -> 104 | C108: ورش عمل للطلاب | D108: ورش قصيرة في البرمجة والتصميم | E108: 20,000 – 60,000 ريال/ورشة | F108: أسعار مقبولة للتدريب العملي | G108: 10,000 – 25,000 ريال | H108: مدربين + أدوات | I108: 10,000 – 35,000 ريال
B109: =1+B108 -> 105 | C109: مسابقات جامعية للألعاب | D109: تنظيم بطولات بين الجامعات | E109: 80,000 – 200,000 ريال | F109: قيمة مناسبة لبطولات تعليمية | G109: 40,000 – 100,000 ريال | H109: تنظيم + جوائز | I109: 40,000 – 100,000 ريال
B110: =1+B109 -> 106 | C110: محتوى تعليمي رقمي | D110: مقاطع فيديو ومحاضرات تفاعلية | E110: 10,000 – 25,000 ريال/مادة | F110: أسعار مشابهة للمنصات التعليمية | G110: 4,000 – 10,000 ريال | H110: إنتاج + مونتاج | I110: 6,000 – 15,000 ريال
B111: =1+B110 -> 107 | C111: تدريب معلمي المدارس | D111: تأهيل المعلمين على توظيف الألعاب | E111: 40,000 – 100,000 ريال/برنامج | F111: قيمة معتمدة في التدريب الحكومي | G111: 20,000 – 50,000 ريال | H111: مدربين + قاعات | I111: 20,000 – 50,000 ريال
B112: =1+B111 -> 108 | C112: محتوى ثقافي تفاعلي | D112: ألعاب تعليمية عن التراث والثقافة | E112: 120,000 – 300,000 ريال | F112: مشابه لمشاريع الثقافة الرقمية | G112: 60,000 – 150,000 ريال | H112: برمجة + تصميم | I112: 60,000 – 150,000 ريال
B113: =1+B112 -> 109 | C113: معارض تعليمية للألعاب | D113: تنظيم معارض جامعية لعرض مشاريع الطلاب | E113: 100,000 – 250,000 ريال | F113: سعر مناسب للمعارض الجامعية | G113: 50,000 – 120,000 ريال | H113: تجهيزات + تنظيم | I113: 50,000 – 130,000 ريال
B114: =1+B113 -> 110 | C114: برامج تدريب عن بعد | D114: كورسات Online في تطوير الألعاب | E114: 30,000 – 80,000 ريال | F114: مشابه لسوق منصات E-learning | G114: 15,000 – 35,000 ريال | H114: منصة + محتوى | I114: 15,000 – 45,000 ريال
B115: =1+B114 -> 111 | C115: مكتبة ألعاب رقمية | D115: توفير مكتبة ألعاب تعليمية للمؤسسات | E115: 50,000 – 120,000 ريال | F115: سعر مرن للجامعات والمدارس | G115: 25,000 – 60,000 ريال | H115: تراخيص + منصة | I115: 25,000 – 60,000 ريال
B116: =1+B115 -> 112 | C116: استشارات بحثية | D116: دعم الجامعات بأبحاث سوق الألعاب | E116: 25,000 – 60,000 ريال/تقرير | F116: قريب من أسعار مراكز الدراسات | G116: 10,000 – 25,000 ريال | H116: فريق بحث + أدوات تحليل | I116: 15,000 – 35,000 ريال
B117: =1+B116 -> 113 | C117: مسابقات تطوير الألعاب | D117: هاكاثونات لطلاب الجامعات | E117: 60,000 – 150,000 ريال | F117: قيمة منطقية لمنافسات تقنية | G117: 30,000 – 70,000 ريال | H117: تنظيم + جوائز | I117: 30,000 – 80,000 ريال
B118: =1+B117 -> 114 | C118: محتوى توعوي للطلاب | D118: حملات عن السلوك الرقمي والأمان | E118: 15,000 – 40,000 ريال | F118: مشابه لبرامج التوعية الوطنية | G118: 6,000 – 15,000 ريال | H118: محتوى + حملات | I118: 9,000 – 25,000 ريال
... B124: =1+B123 -> 120 | C124: Academic Data Exchange | D124: منصة لتبادل بيانات مجهّلة للأبحاث | E124: 80,000 – 200,000 ريال | F124: تدعم الدراسات الأكاديمية | G124: 40,000 – 90,000 ريال | H124: تطوير + إدارة بيانات | I124: 40,000 – 110,000 ريال
B125: =1+B124 -> 121
B126: =1+B125 -> 122 | C126: شراكات بحثية دولية | D126: ربط الجامعات السعودية بجامعات عالمية في مجال الألعاب | E126: 100,000 – 300,000 ريال | F126: قيمة مناسبة لاتفاقيات بحثية | G126: 50,000 – 120,000 ريال | H126: إدارة + محتوى + سفر | I126: 50,000 – 180,000 ريال
B127: =1+B126 -> 123 | C127: فعاليات مجتمعية للألعاب | D127: تنظيم أيام ألعاب مفتوحة للأسر والشباب | E127: 50 – 100 ريال/تذكرة | F127: سعر منخفض يجذب العائلات | G127: 20 – 40 ريال | H127: إيجار موقع + تنظيم | I127: 30 – 60 ريال/شخص | J127: المجتمع العام (الجمهور والأسر)
B128: =1+B127 -> 124 | C128: مهرجانات للألعاب الإلكترونية | D128: مهرجان ترفيهي يضم منصات وتجارب | E128: 100 – 300 ريال/تذكرة | F128: مشابه لفعاليات Gamers8 | G128: 50 – 150 ريال | H128: تنظيم + تجهيزات | I128: 50 – 150 ريال/شخص
B129: =1+B128 -> 125 | C129: باقات عائلية | D129: تذاكر خاصة للعائلات (4–6 أفراد) | E129: 250 – 500 ريال | F129: تشجيع حضور العائلات | G129: 120 – 250 ريال | H129: تنظيم + خدمات ضيافة | I129: 130 – 250 ريال/باقة
B130: =1+B129 -> 126 | C130: تجربة VR/AR ترفيهية | D130: ألعاب واقع افتراضي في المعارض | E130: 20 – 50 ريال/جلسة | F130: سعر معتاد لألعاب VR | G130: 10 – 20 ريال | H130: أجهزة + صيانة | I130: 10 – 30 ريال/جلسة
B131: =1+B130 -> 127 | C131: ورش توعوية للأطفال | D131: تعليم السلوك الرقمي الآمن | E131: 30 – 70 ريال/طفل | F131: سعر مقبول كورش قصيرة | G131: 15 – 30 ريال | H131: مدرب + أدوات | I131: 15 – 40 ريال
B132: =1+B131 -> 128 | C132: مسابقات ميدانية | D132: ألعاب تنافسية في المولات والحدائق | E132: 20 – 50 ريال/مشارك | F132: قيمة رمزية لجذب المشاركين | G132: 10 – 20 ريال | H132: تجهيزات + جوائز | I132: 10 – 30 ريال
B133: =1+B132 -> 129 | C133: تذاكر VIP للفعاليات | D133: تذاكر بميزات إضافية (مقاعد، هدايا) | E133: 500 – 1,000 ريال | F133: تسعير مشابه للـ VIP Events | G133: 250 – 500 ريال | H133: تنظيم + هدايا | I133: 250 – 500 ريال
B134: =1+B133 -> 130 | C134: منتجات تذكارية | D134: بيع قمصان، كابات، مجسمات ماك بلاش | E134: 50 – 200 ريال | F134: قريب من أسعار الميرش في الفعاليات | G134: 20 – 80 ريال | H134: تصنيع + شحن | I134: 30 – 120 ريال
B135: =1+B134 -> 131 | C135: مقاهي ألعاب متنقلة | D135: أكشاك أو عربات تقدم ألعاب وتجارب قصيرة | E135: 20 – 50 ريال/جلسة | F135: سعر مشابه لتجارب المقاهي | G135: 10 – 25 ريال | H135: أجهزة + موقع | I135: 10 – 25 ريال
B136: =1+B135 -> 132 | C136: بطاقات دخول سنوية | D136: بطاقة اشتراك في فعاليات/معارض | E136: 800 – 1,500 ريال | F136: جذابة لهواة الفعاليات | G136: 400 – 700 ريال | H136: تنظيم + منصة | I136: 400 – 800 ريال
B137: =1+B136 -> 133 | C137: جلسات ألعاب عائلية | D137: ألعاب تفاعلية للأسر | E137: 50 – 150 ريال/جلسة | F137: سعر مناسب للأسرة | G137: 25 – 70 ريال | H137: تنظيم + أجهزة | I137: 25 – 80 ريال
...

Sheet الدراسة المالية
C4: البيان | D4: الافتراض | F4: رأس المال العامل الأولي | G4: عدد الأشهر | H4: التكلفة الشهرية (ريال) | I4: التكلفة السنوية (ريال)
C5: معدل التضخم في الأسعار | D5: 0.02 | F5: المصاريف التشغيلية | G5: 3 | H5: ='الدراسة الفنية '!G137 -> 130966.08 | I5: =H5*G5 -> 392898.24
C6: معدل الضريبة | D6: 0.15 | F6: الرواتب والأجور | G6: 3 | H6: ='الدراسة الفنية '!G38/12 -> 27500 | I6: =H6*G6 -> 82500
C7: معدل الخصم السائد | D7: 0.05 | F7: راس المال العامل الأولي المطلوب | I7: =SUM(I5:I6) -> 475398.24
F10: ملخص التكاليف الرأسمالية | G10: التكلفة ريال | H10: نسبة من الإجمالي | I10: المرجع
F11: التجهيزات والأعمال الأنشائية | G11: ='الدراسة الفنية '!I52 -> 2.9794299e+08 | H11: =G11/G$17 -> #REF! | I11: الدراسة الفنية
F12: الأجهزة والمعدات الرياضية | G12: ='الدراسة الفنية '!I78 -> 0 | H12: =G12/G$17 -> #REF! | I12: الدراسة الفنية
F13: أجهزة الحاسوب والأثاث | G13: ='الدراسة الفنية '!I101 -> 10504 | H13: =G13/G$17 -> #REF! | I13: الدراسة الفنية
F14: مصاريف التأسيس القانونية | G14: =#REF! -> #REF! | H14: =G14/G$17 -> #REF! | I14: الدراسة القانوينة
F15: مصاريف الحملة التسويقية | G15: =#REF! -> #REF! | H15: =G15/G$17 -> #REF! | I15: الدراسة التسويقية
F16: رأس المال العامل الأولي | G16: =I7 -> 475398.24 | H16: =G16/G$17 -> #REF! | I16: الدراسة المالية
F17: إجمالي التكاليف الرأسمالية | G17: =SUM(G11:G16) -> #REF! | H17: =G17/G$17 -> #REF!
F20: ملخص التكاليف الرأسمالية | G20: المسبح | H20: البادل | I20: الملعب المتعدد الأغراض | J20: الصالة الرياضية | K20: الإجمالي
F21: التجهيزات والأعمال الأنشائية | G21: ='الدراسة الفنية '!I46 -> 283091.67 | H21: ='الدراسة الفنية '!I47 -> 79963.333 | I21: ='الدراسة الفنية '!I48 -> 0 | J21: ='الدراسة الفنية '!I49 -> 2.9463e+08 | K21: =SUM(G21:J21) -> 2.9499305e+08
F22: الأجهزة والمعدات الرياضية | G22: =SUM('الدراسة الفنية '!R83:R86)+SUM('الدراسة الفنية '!R91:R92) -> 0 | H22: =SUM('الدراسة الفنية '!R61:R64)*1.01 -> 0 | I22: =SUM('الدراسة الفنية '!R105:R108)*1.01 -> 0 | J22: =SUM('الدراسة الفنية '!R142:R145)*1.01 -> 0 | K22: =SUM(G22:J22) -> 0
F23: أجهزة الحاسوب والأثاث | G23: =SUM('الدراسة الفنية '!R87:R90)*1.01 -> 0 | H23: =SUM('الدراسة الفنية '!R65:R68)*1.01 -> 0 | I23: =SUM('الدراسة الفنية '!R109:R112)*1.01 -> 0 | J23: =SUM('الدراسة الفنية '!R146:R149)*1.01 -> 0 | K23: =SUM(G23:J23) -> 0
F24: مصاريف التأسيس القانونية | G24: =$G14/4 -> #REF! | H24: =$G14/4 -> #REF! | I24: =$G14/4 -> #REF! | J24: =$G14/4 -> #REF! | K24: =SUM(G24:J24) -> #REF!
F25: مصاريف الحملة التسويقية | G25: =$G15/4 -> #REF! | H25: =$G15/4 -> #REF! | I25: =$G15/4 -> #REF! | J25: =$G15/4 -> #REF! | K25: =SUM(G25:J25) -> #REF!
F26: رأس المال العامل الأولي | G26: =$I7/4 -> 118849.56 | H26: =$I7/4 -> 118849.56 | I26: =$I7/4 -> 118849.56 | J26: =$I7/4 -> 118849.56 | K26: =SUM(G26:J26) -> 475398.24
F27: إجمالي التكاليف الرأسمالية | G27: =SUM(G21:G26) -> #REF! | H27: =SUM(H21:H26) -> #REF! | I27: =SUM(I21:I26) -> #REF! | J27: =SUM(J21:J26) -> #REF! | K27: =SUM(K21:K26) -> #REF!

Sheet الدراسة الفنية 
D3: معدل التضخم السنوي | E3: 0.02
C5: # | D5: نوع الوظيفة | E5: العدد | F5: الراتب المتوقع | G5: الإجمالي للسنة 1
C6: المسبح | D6: مدير المسبح و مشرف السباحة | E6: 1 | F6: 2000 | G6: =F6*E6*12 -> 24000
D7: مستقبل العملاء ومحاسب | E7: 1 | F7: 1500 | G7: =F7*E7*12 -> 18000
D8: موظف صيانة ونظافة | E8: 1 | F8: 1500 | G8: =F8*E8*12 -> 18000
D9: موظف مبيعات وتسويق | E9: 1 | F9: 1500 | G9: =F9*E9*12 -> 18000
D12: إجمالي رواتب المسبح | G12: =SUM(G6:G11) -> 78000
C13: # | D13: نوع الوظيفة | E13: العدد | F13: الراتب المتوقع | G13: الإجمالي للسنة 1
C14: البادل | D14: مدير الموقع و مشرف الموقع | E14: 1 | F14: 2000 | G14: =F14*E14*12 -> 24000
D15: مدرب ومشرف الموقع | E15: 1 | F15: 1500 | G15: =F15*E15*12 -> 18000
D16: مستقبل العملاء ومحاسب | E16: 1 | F16: 1500 | G16: =F16*E16*12 -> 18000
D17: موظف صيانة ونظافة | E17: 1 | F17: 1500 | G17: =F17*E17*12 -> 18000
D18: موظف مبيعات وتسويق | E18: 1 | F18: 1500 | G18: =F18*E18*12 -> 18000
D20: إجمالي رواتب البادل | G20: =SUM(G14:G19) -> 96000
C21: # | D21: نوع الوظيفة | E21: العدد | F21: الراتب المتوقع | G21: الإجمالي للسنة 1
C22: ملعب متعدد الأغراض | D22: مدير الملعب ومشرف على الموقع | E22: 1 | F22: 2000 | G22: =F22*E22*12 -> 24000
D23: مستقبل العملاء ومحاسب | E23: 1 | F23: 1500 | G23: =F23*E23*12 -> 18000
D24: موظف مبيعات وتسويق | E24: 1 | F24: 1500 | G24: =F24*E24*12 -> 18000
D25: موظف صيانة ونظافة | E25: 1 | F25: 1500 | G25: =F25*E25*12 -> 18000
D28: إجمالي رواتب الملعب | G28: =SUM(G22:G27) -> 78000
C29: # | D29: نوع الوظيفة | E29: العدد | F29: الراتب المتوقع | G29: الإجمالي للسنة 1
C30: الصالة الرياضية | D30: مدير الصالة الرياضية ومشرف على الموقع | E30: 1 | F30: 2000 | G30: =F30*E30*12 -> 24000
D31: مستقبل العملاء ومحاسب | E31: 1 | F31: 1500 | G31: =F31*E31*12 -> 18000
D32: موظف مبيعات وتسويق | E32: 1 | F32: 1500 | G32: =F32*E32*12 -> 18000
D33: موظف صيانة ونظافة | E33: 1 | F33: 1500 | G33: =F33*E33*12 -> 18000
D36: إجمالي رواتب الصالة الرياضية | G36: =SUM(G30:G35) -> 78000
D38: إجمالي رواتب النادي للسنة الأولى | G38: =SUM(G36,G28,G20,G12) -> 330000
C44: # | D44: البيان | E44: الغرض | F44: المساحة متر/مربع | G44: تكلفة المتر/ريال | H44: % الاستهلاك | I44: إجمالي التكلفة /ريال
C46: 1 | D46: مساحة المسبح | E46: تكلفة التشطيب | F46: 700 | G46: ='دراسة الموارد التقنية '!F61 -> 404.41667 | H46: 0.05 | I46: =G46*F46 -> 283091.67
C47: 2 | D47: مساحة البادل | E47: تكلفة التشطيب | F47: 700 | G47: ='دراسة الموارد التقنية '!F81 -> 114.23333 | H47: 0.05 | I47: =G47*F47 -> 79963.333
C48: 3 | D48: مساحة الملعب متعدد الأغراض | E48: تكلفة التشطيب | F48: 1000 | G48: ='دراسة الموارد التقنية '!F42 -> 0 | H48: 0.05 | I48: =G48*F48 -> 0
C49: 4 | D49: مساحة الصالة الرياضة | E49: تكلفة التشطيب | F49: 300 | G49: ='دراسة الموارد التقنية '!F24 -> 982100 | H49: 0.05 | I49: =G49*F49 -> 2.9463e+08
I50: =G50*F50 -> 0
C51: تكاليف غير منظورة | G51: % | H51: 0.01 | I51: =SUM(I46:I50)*H51 -> 2949930.5
C52: إجمالي تكاليف المباني والإنشاءات | I52: =SUM(I46:I51) -> 2.9794299e+08
C53: إجمالي م استهلاك المباني والإنشاءات | I53: =SUMPRODUCT(H46:H49,I46:I49) -> 14749653
C54: إجمالي الصيانة السنوية المباني والإنشاءات | G54: % | H54: 0.01 | I54: =H54*I52 -> 2979429.9
C58: # | D58: البيان | E58: القسم | F58: العدد | G58: التكلفة/ريال | H58: % الاستهلاك | I58: إجمالي التكلفة /ريال
C60: 1 | D60: مضخة لتدوير المياه | E60: المسبح | F60: 1 | G60: =P83 -> 0 | H60: 0.15 | I60: =G60*F60 -> 0
C61: 2 | D61: الأرضية الصناعية شبكة و أعمدة البادل | E61: البادل | F61: 1 | G61: =P61 -> 0 | H61: 0.15 | I61: =G61*F61 -> 0
C62: 3 | D62: الأرضية الرسوم متعددة | E62: ملعب متعدد الأغراض | F62: 1 | G62: =P105 -> 0 | H62: 0.15 | I62: =G62*F62 -> 0
C63: 4 | D63: أرضية صناعية قابلة لتحمل الصدمات | E63: الصالة الرياضية | F63: =O142 -> 0 | G63: =P142 -> 0 | H63: 0.15 | I63: =G63*F63 -> 0
C64: 5 | D64: فلتر تقنية المياه | E64: المسبح | F64: 1 | G64: =P84 -> 0 | H64: 0.15 | I64: =G64*F64 -> 0
C65: 6 | D65: الإضاءة الخارجية للملعب + الداخلية | E65: البادل | F65: 1 | G65: =P62 -> 0 | H65: 0.15 | I65: =G65*F65 -> 0
C66: 7 | D66: الإضاءة الخارجية للملعب + الداخلية | E66: ملعب متعدد الأغراض | F66: 1 | G66: =P106 -> 0 | H66: 0.15 | I66: =G66*F66 -> 0
C67: 8 | D67: الإضاءة الخارجية للملعب + الداخلية | E67: الصالة الرياضية | F67: 1 | G67: =P143 -> 0 | H67: 0.15 | I67: =G67*F67 -> 0
C68: 9 | D68: خزان تحكم بالكيماويات | E68: المسبح | F68: 1 | G68: =P85 -> 0 | H68: 0.15 | I68: =G68*F68 -> 0
C69: 10 | D69: معدات اللعب والتدريب ( البادل) | E69: البادل | F69: 1 | G69: =P63 -> 0 | H69: 0.15 | I69: =G69*F69 -> 0
C70: 11 | D70: معدات اللعب والتدريب ( ملعب متعدد الأغراض) | E70: ملعب متعدد الأغراض | F70: 1 | G70: =P107 -> 0 | H70: 0.15 | I70: =G70*F70 -> 0
C71: 12 | D71: معدات اللعب والتدريب ( الصالة الرياضة) | E71: الصالة الرياضية | F71: 1 | G71: =P144 -> 0 | H71: 0.15 | I71: =G71*F71 -> 0
C72: 13 | D72: أنظمة السلامة والأنذار والاسعافات وحواجز الحماية | E72: المسبح | F72: 1 | G72: =P86 -> 0 | H72: 0.15 | I72: =G72*F72 -> 0
C73: 14 | D73: أنظمة السلامة والأنذار والاسعافات وحواجز الحماية | E73: البادل | F73: 1 | G73: =P64 -> 0 | H73: 0.15 | I73: =G73*F73 -> 0
C74: 15 | D74: أنظمة السلامة والأنذار والاسعافات وحواجز الحماية | E74: ملعب متعدد الأغراض | F74: 1 | G74: =P108 -> 0 | H74: 0.15 | I74: =G74*F74 -> 0
C75: 16 | D75: أنظمة السلامة والأنذار والاسعافات وحواجز الحماية | E75: الصالة الرياضية | F75: 1 | G75: =P145 -> 0 | H75: 0.15 | I75: =G75*F75 -> 0
C76: 17 | D76: الإضاءة الخارجية للملعب + الداخلية | E76: المسبح | F76: 1 | G76: =P92 -> 0 | H76: 0.15 | I76: =G76*F76 -> 0
C77: تكاليف غير منظورة | G77: % | H77: 0.01 | I77: =SUM(I60:I75)*H77 -> 0
C78: إجمالي تكاليف المعدات والأجهزة الرياضية | I78: =SUM(I60:I77) -> 0
C79: إجمالي م.استهلاك االمعدات والأجهزة الرياضية | I79: =SUMPRODUCT(H60:H75,I60:I75) -> 0
C80: إجمالي الصيانة السنوية للمعدات والأجهزة الرياضية | G80: % | H80: 0.01 | I80: =H80*I78 -> 0
C82: # | D82: البيان | E82: القسم | F82: العدد | G82: التكلفة/ريال | H82: % الاستهلاك | I82: إجمالي التكلفة /ريال
C84: 1 | D84: أجهزة الحاسوب | E84: المسبح | F84: 1 | G84: 2000 | H84: 0.2 | I84: =G84*F84 -> 2000
C85: 2 | D85: أجهزة الحاسوب | E85: البادل | F85: 1 | G85: 2000 | H85: 0.2 | I85: =G85*F85 -> 2000
C86: 3 | D86: أجهزة الحاسوب | E86: ملعب متعدد الأغراض | F86: 1 | G86: 2000 | H86: 0.2 | I86: =G86*F86 -> 2000
C87: 4 | D87: أجهزة الحاسوب | E87: الصالة الرياضية | F87: 1 | G87: 2000 | H87: 0.2 | I87: =G87*F87 -> 2000
C88: 5 | D88: الطابعات | E88: المسبح | F88: 1 | G88: 300 | H88: 0.2 | I88: =G88*F88 -> 300
C89: 6 | D89: الطابعات | E89: البادل | F89: 1 | G89: 300 | H89: 0.2 | I89: =G89*F89 -> 300
C90: 7 | D90: الطابعات | E90: ملعب متعدد الأغراض | F90: 1 | G90: 300 | H90: 0.2 | I90: =G90*F90 -> 300
C91: 8 | D91: الطابعات | E91: الصالة الرياضية | F91: 1 | G91: 300 | H91: 0.2 | I91: =G91*F91 -> 300
C92: 9 | D92: كراسي | E92: المسبح | F92: =O89 -> 0 | G92: 40 | H92: 0.1 | I92: =G92*F92 -> 0
C93: 10 | D93: كراسي | E93: البادل | F93: =O67 -> 0 | G93: 40 | H93: 0.1 | I93: =G93*F93 -> 0
C94: 11 | D94: كراسي | E94: ملعب متعدد الأغراض | F94: =O111 -> 0 | G94: 40 | H94: 0.1 | I94: =G94*F94 -> 0
C95: 12 | D95: كراسي | E95: الصالة الرياضية | F95: =O148 -> 0 | G95: 40 | H95: 0.1 | I95: =G95*F95 -> 0
C96: 13 | D96: طاولة صغيرة | E96: المسبح | F96: 1 | G96: 300 | H96: 0.1 | I96: =G96*F96 -> 300
C97: 14 | D97: طاولة صغيرة | E97: البادل | F97: 1 | G97: 300 | H97: 0.1 | I97: =G97*F97 -> 300
C98: 15 | D98: طاولة صغيرة | E98: ملعب متعدد الأغراض | F98: 1 | G98: 300 | H98: 0.1 | I98: =G98*F98 -> 300
C99: 16 | D99: طاولة صغيرة | E99: الصالة الرياضية | F99: 1 | G99: 300 | H99: 0.1 | I99: =G99*F99 -> 300
C100: تكاليف غير منظورة | G100: % | H100: 0.01 | I100: =SUM(I84:I99)*H100 -> 104
C101: إجمالي تكاليف أجهزة الحاسوب والأثاث | I101: =SUM(I84:I100) -> 10504
C102: إجمالي م.استهلاك أجهزة الحاسوب والأثاث | I102: =SUMPRODUCT(I84:I99,H84:H99) -> 1960
C103: إجمالي الصيانة السنوية أجهزة الحاسوب والأثاث | G103: % | H103: 0.01 | I103: =H103*I101 -> 105.04
I105: =SUM(I101,I78,I52) -> 2.9795349e+08
I106: =SUM(I102,I79,I53) -> 14751613
C108: # | D108: البيان | F108: تكلفة شهرية ريال | G108: تكلفة سنوية ريال | H108: المتغير % | I108: التكالف المتغيرة | J108: التكاليف الثابتة
C109: 1 | D109: استهلاك مياه للمسبح | F109: 400 | G109: =F109*12 -> 4800 | H109: 0.4 | I109: =H109*G109 -> 1920 | J109: =G109-I109 -> 2880
C110: 2 | D110: استهلاك كهرباء للمسبح | F110: 2500 | G110: =F110*12 -> 30000 | H110: 0.4 | I110: =H110*G110 -> 12000 | J110: =G110-I110 -> 18000
C111: 3 | D111: مصاريف التأمين | F111: 500 | G111: =F111*12 -> 6000 | H111: 0.4 | I111: =H111*G111 -> 2400 | J111: =G111-I111 -> 3600
C112: 4 | D112: مصاريف الاتصالات للمسبح | F112: 50 | G112: =F112*12 -> 600 | H112: 0.5 | I112: =H112*G112 -> 300 | J112: =G112-I112 -> 300
C113: 5 | D113: مصاريف النظافة للمسبح | F113: 300 | G113: =F113*12 -> 3600 | H113: 0.6 | I113: =H113*G113 -> 2160 | J113: =G113-I113 -> 1440
C114: 6 | D114: رسوم بلدية | F114: 100 | G114: =F114*12 -> 1200 | H114: 0 | I114: =H114*G114 -> 0 | J114: =G114-I114 -> 1200
C115: 7 | D115: رسوم الغرفة التجارية | F115: 50 | G115: =F115*12 -> 600 | H115: 0 | I115: =H115*G115 -> 0 | J115: =G115-I115 -> 600
C116: 8 | D116: مدد | F116: =38*4 -> 152 | G116: =F116*12 -> 1824 | H116: 0.6 | I116: =H116*G116 -> 1094.4 | J116: =G116-I116 -> 729.6
C117: 9 | D117: قوى | F117: =4*133 -> 532 | G117: =F117*12 -> 6384 | H117: 0.6 | I117: =H117*G117 -> 3830.4 | J117: =G117-I117 -> 2553.6
C118: 10 | D118: قرطاسية ومطبوعات | F118: =200 -> 200 | G118: =F118*12 -> 2400 | H118: 0.4 | I118: =H118*G118 -> 960 | J118: =G118-I118 -> 1440
C119: 11 | D119: رسوم اشتراكات متنوعة | F119: 150 | G119: =F119*12 -> 1800 | H119: 0 | I119: =H119*G119 -> 0 | J119: =G119-I119 -> 1800
C120: 13 | D120: استهلاك مياه لملعب البادل | F120: 50 | G120: =F120*12 -> 600 | H120: 0.4 | I120: =H120*G120 -> 240 | J120: =G120-I120 -> 360
C121: =C120+1 -> 14 | D121: استهلاك كهرباء لملعب البادل | F121: 1500 | G121: =F121*12 -> 18000 | H121: 0.4 | I121: =H121*G121 -> 7200 | J121: =G121-I121 -> 10800
C122: =C121+1 -> 15 | D122: استهلاك مياه للصالة الرياضية | F122: 50 | G122: =F122*12 -> 600 | H122: 0.4 | I122: =H122*G122 -> 240 | J122: =G122-I122 -> 360
C123: =C122+1 -> 16 | D123: استهلاك كهرباء للصالة الرياضية | F123: 1500 | G123: =F123*12 -> 18000 | H123: 0.4 | I123: =H123*G123 -> 7200 | J123: =G123-I123 -> 10800
C124: =C123+1 -> 17 | D124: استهلاك مياه للملعب متعدد الأغراض | F124: 100 | G124: =F124*12 -> 1200 | H124: 0.4 | I124: =H124*G124 -> 480 | J124: =G124-I124 -> 720
C125: =C124+1 -> 18 | D125: استهلاك كهرباء ل للملعب متعدد الأغراض | F125: 2000 | G125: =F125*12 -> 24000 | H125: 0.4 | I125: =H125*G125 -> 9600 | J125: =G125-I125 -> 14400
...

Sheet تقدير الإيرادات 
D4: الخدمات | F4: اعداد العملاء المتوقع | G4: معدل النمو السنوي | H4: متوسط أسعار الخدمات | I4: السنة 1
D5: المنصة | E5: شهري | F5: 300 | G5: 0.07 | H5: ='اسعار الخدمات'!I183 -> 75.75 | I5: =H5*F5*12 -> 272700
D6: الإعلامي | E6: شهري | F6: 100 | G6: 0.1 | H6: ='اسعار الخدمات'!I5 -> الربح المتوقع (ريال) | I6: =H6*F6*12 -> #VALUE!
D7: الاستديو | E7: شهري | F7: 105 | G7: 0.07 | H7: ='اسعار الخدمات'!I160 -> 198.33333 | I7: =H7*F7*12 -> 249900
D8: أخرى | E8: شهري | F8: 90 | G8: 0.07 | H8: ='اسعار الخدمات'!I172 -> 177.5 | I8: =H8*F8*12 -> 191700
I9: =SUM(I5:I8) -> #VALUE!
D12: الخدمات | F12: السنة 2 | G12: السنة 3 | H12: السنة 4 | I12: السنة 5
D13: المنصة | F13: =I5*(1+G5) -> 291789 | G13: =F13*(1+$G5) -> 312214.23 | H13: =G13*(1+$G5) -> 334069.23 | I13: =H13*(1+$G5) -> 357454.07
D14: الإعلامي | F14: =I6*(1+G6) -> #VALUE! | G14: =F14*(1+$G6) -> #VALUE! | H14: =G14*(1+$G6) -> #VALUE! | I14: =H14*(1+$G6) -> #VALUE!
D15: الاستديو | F15: =I7*(1+G7) -> 267393 | G15: =F15*(1+$G7) -> 286110.51 | H15: =G15*(1+$G7) -> 306138.25 | I15: =H15*(1+$G7) -> 327567.92
D16: أخرى | F16: =I8*(1+G8) -> 205119 | G16: =F16*(1+$G8) -> 219477.33 | H16: =G16*(1+$G8) -> 234840.74 | I16: =H16*(1+$G8) -> 251279.6
F17: =SUM(F13:F16) -> #VALUE! | G17: =SUM(G13:G16) -> #VALUE! | H17: =SUM(H13:H16) -> #VALUE! | I17: =SUM(I13:I16) -> #VALUE!

Sheet اسعار الخدمات
C3: الخدمات المقدمة من ماك بلاش وتوصيفها
B4: # | C4: البند | D4: الوصف | E4: القيمة | F4: لماذا تم اختيار القيمة ؟ | G4: التكلفة | H4: كيف تم احتساب التكلفة ؟ | I4: الربح المتوقع بالريال | J4: الفئة
C5: البند | D5: الوصف | E5: القيمة (سعر البيع) | F5: لماذا تم اختيار القيمة؟ | G5: التكلفة | H5: كيف تم احتساب التكلفة؟ | I5: الربح المتوقع (ريال) | J5: الأفراد
C6: اشتراكات مميزة (Premium) | D6: مزايا إضافية مثل محتوى حصري وإزالة إعلانات | E6: 30 ريال/شهر | F6: منافس لخدمات عالمية مثل Spotify Gaming | G6: 10 ريال/مستخدم | H6: استضافة + صيانة + دعم فني | I6: 20 ريال/مستخدم
C7: شراء عناصر رقمية | D7: Skins وأدوات وبطاقات داخل الألعاب | E7: 20 – 100 ريال | F7: مشابه لأسعار Fortnite وPUBG | G7: 5 – 20 ريال | H7: رسوم تطوير/ترخيص | I7: 15 – 80 ريال
C8: رسوم بطولات إلكترونية | D8: مشاركة في بطولات بجوائز | E8: 100 ريال/مشارك | F8: سعر متوسط للبطولات المحلية | G8: 40 ريال | H8: تنظيم + جوائز | I8: 60 ريال/مشارك
C9: بطاقات شحن الألعاب | D9: بطاقات بلايستيشن، إكس بوكس، ستيم | E9: 50 – 300 ريال | F9: مطابق لأسعار السوق | G9: 45 – 280 ريال | H9: شراء جملة من الموردين | I9: 5 – 20 ريال
C10: متجر ألعاب رقمي | D10: شراء ألعاب مباشرة عبر المنصة | E10: 100 – 300 ريال | F10: مشابه لـ Steam وEpic | G10: 80 – 250 ريال | H10: تراخيص توزيع الألعاب | I10: 20 – 50 ريال
C11: لعبة الشهر | D11: اشتراك يمنح لعبة كل شهر | E11: 40 ريال/شهر | F11: مثل Xbox Game Pass مصغر | G11: 20 ريال | H11: تراخيص ألعاب | I11: 20 ريال
C12: تأجير حسابات ألعاب | D12: استئجار حسابات لتجربة ألعاب مميزة | E12: 25 ريال/يوم | F12: سعر جذاب للهواة | G12: 10 ريال | H12: صيانة الحساب + تراخيص | I12: 15 ريال
C13: تدريب شخصي (Coaching) | D13: جلسة مع لاعب محترف | E13: 150 ريال/ساعة | F13: سعر قريب من سوق التدريب المحلي | G13: 70 ريال | H13: أتعاب المدرب | I13: 80 ريال
C14: ورش عمل مجتمعية | D14: ورش تعليم صناعة الألعاب أو البث | E14: 200 ريال/ورشة | F14: مقبول كورش قصيرة | G14: 100 ريال | H14: منصة + مدرب | I14: 100 ريال
C15: مسابقات أسبوعية | D15: تحديات بجوائز رمزية | E15: 20 ريال/مشارك | F15: لجذب التفاعل | G15: 10 ريال | H15: جوائز + استضافة | I15: 10 ريال
C16: خدمة إعادة البث (Replay) | D16: حفظ وإعادة لقطات اللعب | E16: 15 ريال/شهر | F16: مشابه لخدمات Twitch Replay | G16: 5 ريال | H16: سيرفر + تخزين | I16: 10 ريال
C17: عضوية عائلية | D17: اشتراك لعدة مستخدمين (Family Pack) | E17: 100 ريال/شهر | F17: مشابه لخدمات Netflix Family | G17: 40 ريال | H17: استضافة + دعم | I17: 60 ريال
... C25: نظام الولاء والنقاط | D25: نقاط تستبدل بمكافآت | E25: 20 ريال/اشتراك | F25: يزيد التفاعل | G25: 5 ريال | H25: تطوير + إدارة | I25: 15 ريال
C26: إدارة الحملات التسويقية | D26: تنظيم حملات المؤثر مع الشركات | E26: 20,000 – 100,000 ريال/حملة | F26: منافس لسوق إدارة المؤثرين | G26: 10,000 – 50,000 ريال | H26: فريق إدارة + إعلانات | I26: 10,000 – 50,000 ريال | J26: للمؤثرين
C27: إنتاج فيديوهات مخصصة | D27: مونتاج فيديوهات ترويجية للبثوص | E27: 5,000 – 15,000 ريال/فيديو | F27: سعر سوقي لإنتاج المحتوى | G27: 3,000 – 7,000 ريال | H27: تصوير + مونتاج | I27: 2,000 – 8,000 ريال
C28: تصميم الهوية البصرية | D28: شعار + بانر + ثيمات للبث | E28: 3,000 – 8,000 ريال | F28: متوافق مع أسعار المصممين | G28: 1,500 – 4,000 ريال | H28: تصميم + مراجعات | I28: 1,500 – 4,000 ريال
C29: استوديو تصوير مؤقت | D29: تأجير استوديو مع معدات | E29: 2,500 – 7,500 ريال/يوم | F29: مثل أسعار استوديوهات جدة/الرياض | G29: 1,000 – 4,000 ريال | H29: تأجير معدات + مساحة | I29: 1,500 – 3,500 ريال
C30: خدمة البث المباشر الاحترافي | D30: إعداد وإدارة بث مباشر | E30: 10,000 – 25,000 ريال/فعالية | F30: مشابه لشركات البث | G30: 5,000 – 12,000 ريال | H30: معدات + تقنيين | I30: 5,000 – 13,000 ريال
C31: إدارة حسابات التواصل | D31: جدولة المحتوى + الردود | E31: 3,000 – 10,000 ريال/شهر | F31: سعر السوق لإدارة الحسابات | G31: 1,500 – 4,000 ريال | H31: مدير حساب + أدوات | I31: 1,500 – 6,000 ريال
C32: تحليلات أداء المحتوى | D32: تقارير أداء وتفاعل الجمهور | E32: 2,000 – 5,000 ريال/تقرير | F32: قيمة عادلة مقابل البيانات | G32: 800 – 2,000 ريال | H32: أدوات تحليل | I32: 1,200 – 3,000 ريال
C33: عقود رعاية وشراكات | D33: صياغة عقود قانونية للمؤثرين | E33: 4,000 – 12,000 ريال/عقد | F33: متوافق مع مكاتب المحاماة | G33: 2,000 – 5,000 ريال | H33: استشارات قانونية | I33: 2,000 – 7,000 ريال
C34: تدريب المؤثرين | D34: ورش تدريب على تحسين البث | E34: 1,500 – 3,000 ريال/ورشة | F34: أسعار دورات تطوير المهارات | G34: 700 – 1,500 ريال | H34: مدرب + منصة | I34: 800 – 1,500 ريال
C35: متجر إلكتروني شخصي | D35: إنشاء متجر لبيع منتجات المؤثر | E35: 8,000 – 20,000 ريال | F35: سعر شبيه بـ Shopify Solutions | G35: 3,000 – 8,000 ريال | H35: تطوير متجر + تصميم | I35: 5,000 – 12,000 ريال
C36: ربط مع شركات رعاية | D36: تقديم المؤثر لشركات مناسبة | E36: 5,000 ريال/صفقة | F36: قيمة بسيطة لتحفيز الرعايات | G36: 1,500 ريال | H36: علاقات + إدارة | I36: 3,500 ريال
C37: خدمة الإنتاج الصوتي | D37: تسجيل وتعليق صوتي احترافي | E37: 1,500 – 4,000 ريال | F37: مطابق لسوق الإنتاج الصوتي | G37: 700 – 1,800 ريال | H37: استوديو + معدات | I37: 800 – 2,200 ريال
C38: إدارة حقوق المحتوى | D38: حماية الفيديوهات من السرقة | E38: 4,000 – 10,000 ريال/شهر | F38: متوافق مع خدمات حماية المحتوى | G38: 2,000 – 4,000 ريال | H38: نظام حماية + متابعة | I38: 2,000 – 6,000 ريال
... C45: On-Demand Merch 2-Hour | D45: متجر مرش سريع بالطباعة عند الطلب خلال ساعتين | E45: 50 – 200 ريال/منتج | F45: منتج فوري يعزز المبيعات | G45: 25 – 80 ريال | H45: طباعة محلية + لوجستيات | I45: 25 – 120 ريال
C46: إعلانات ورعايات داخل المنصة | D46: حجز مساحات إعلانية داخل المنصة أو أثناء البث | E46: 100,000 – 500,000 ريال/حملة | F46: منافس لمنصات مثل Twitch وYouTube Gaming | G46: 50,000 – 150,000 ريال | H46: إنتاج محتوى + إدارة الحملة | I46: 50,000 – 350,000 ريال | J46: لشركات التجارية
C47: رعاية البطولات الإلكترونية | D47: شراكة مع ماك بلاش لرعاية الفعاليات | E47: 150,000 – 600,000 ريال/بطولة | F47: متوافق مع السوق السعودي (Gamers8) | G47: 80,000 – 250,000 ريال | H47: تنظيم البطولة + الجوائز | I47: 70,000 – 350,000 ريال
C48: إنتاج محتوى دعائي للشركات | D48: فيديوهات تسويقية للألعاب أو المنتجات | E48: 30,000 – 80,000 ريال/فيديو | F48: سعر السوق للإنتاج الإعلامي | G48: 15,000 – 40,000 ريال | H48: تصوير + إخراج + مونتاج | I48: 15,000 – 40,000 ريال
C49: منصة إطلاق المنتجات (Product Launch) | D49: بث وإعلان عن منتجات جديدة عبر ماك بلاش | E49: 50,000 – 200,000 ريال | F49: مشابه لسوق الإطلاقات الرقمية | G49: 25,000 – 80,000 ريال | H49: تجهيز منصة + حملات | I49: 25,000 – 120,000 ريال
C50: متجر إلكتروني مخصص | D50: إنشاء متجر للشركات لبيع منتجات ألعاب أو إكسسوارات | E50: 40,000 – 120,000 ريال | F50: أسعار مقاربة لتصميم متاجر Shopify | G50: 20,000 – 50,000 ريال | H50: تطوير + تصميم | I50: 20,000 – 70,000 ريال
C51: استضافة بثوث الشركات | D51: بث فعاليات ومؤتمرات الشركات عبر المنصة | E51: 25,000 – 100,000 ريال/فعالية | F51: أسعار مقاربة لخدمات البث المحترفة | G51: 10,000 – 40,000 ريال | H51: معدات + سيرفرات | I51: 15,000 – 60,000 ريال
C52: تقارير تحليل اللاعبين (Analytics) | D52: تقارير عن سلوك اللاعبين لصالح الشركات | E52: 20,000 – 50,000 ريال/تقرير | F52: قيمة سوقية للبيانات الضخمة | G52: 8,000 – 20,000 ريال | H52: أدوات BI + فريق تحليل | I52: 12,000 – 30,000 ريال
C53: إدارة حملات تسويق رقمية | D53: حملات تسويقية موجهة لجمهور اللاعبين | E53: 30,000 – 150,000 ريال | F53: أسعار مشابهة لشركات التسويق الكبرى | G53: 15,000 – 70,000 ريال | H53: إعلانات ممولة + إدارة | I53: 15,000 – 80,000 ريال
C54: تطوير ألعاب للشركات (Advergames) | D54: ألعاب مصممة خصيصًا للتسويق | E54: 120,000 – 400,000 ريال | F54: أسعار السوق الإقليمي للألعاب التفاعلية | G54: 70,000 – 200,000 ريال | H54: برمجة + تصميم + اختبار | I54: 50,000 – 200,000 ريال
C55: تنظيم فعاليات ألعاب للشركات | D55: فعاليات ترفيهية أو تسويقية عبر الألعاب | E55: 80,000 – 300,000 ريال | F55: متوافق مع السوق السعودي | G55: 40,000 – 120,000 ريال | H55: تنظيم + تجهيز + محتوى | I55: 40,000 – 180,000 ريال
C56: ربط مع المؤثرين | D56: توصيل الشركات بالمؤثرين المناسبين | E56: 20,000 – 80,000 ريال/حملة | F56: نفس أسعار وكالات المؤثرين | G56: 10,000 – 40,000 ريال | H56: أتعاب المؤثرين + إدارة | I56: 10,000 – 40,000 ريال
C57: إنتاج محتوى تفاعلي | D57: اختبارات ومسابقات موجهة لمنتجات الشركات | E57: 15,000 – 50,000 ريال | F57: أسعار مناسبة لحملات تفاعلية | G57: 7,000 – 20,000 ريال | H57: تصميم + تطوير | I57: 8,000 – 30,000 ريال
C58: خدمات تصوير احترافية | D58: تصوير منتجات شركات الألعاب/التقنية | E58: 8,000 – 25,000 ريال/جلسة | F58: أسعار السوق السعودي للتصوير | G58: 4,000 – 12,000 ريال | H58: معدات + فريق تصوير | I58: 4,000 – 13,000 ريال
... C64: Retail-to-Gamer Bridge | D64: ربط عروض المتاجر التقليدية بمكافآت داخل الألعاب | E64: 20,000 – 60,000 ريال | F64: يقيس أثر المبيعات عبر الإنترنت والواقع | G64: 10,000 – 25,000 ريال | H64: تطوير + تكامل API | I64: 10,000 – 35,000 ريال
C65: خدمات استضافة منتجات الشركات | D65: عرض منتجات الشركات داخل المنصة (Marketplace B2B) | E65: 5% عمولة | F65: مشابه لـ Amazon/Ebay | G65: 0.02 | H65: رسوم دفع + إدارة | I65: 3% عمولة
C66: تقارير سوق الألعاب | D66: تقارير تحليلية عن السوق والاتجاهات | E66: 15,000 – 40,000 ريال/تقرير | F66: قيمة تنافسية مقارنة بشركات الأبحاث | G66: 6,000 – 15,000 ريال | H66: فريق بحث + أدوات تحليل | I66: 9,000 – 25,000 ريال | J66: المستثمرين
C67: دراسات جدوى لمشاريع الألعاب | D67: دراسة جدوى لمشاريع استثمارية في الألعاب | E67: 50,000 – 120,000 ريال | F67: أسعار معتادة في مكاتب الاستشارات | G67: 25,000 – 60,000 ريال | H67: محللين ماليين + مستشارين | I67: 25,000 – 60,000 ريال
C68: استشارات استثمارية | D68: جلسات استشارية موجهة للاستثمار في قطاع الألعاب | E68: 5,000 – 15,000 ريال/جلسة | F68: مشابه لأسعار مكاتب استشارية متخصصة | G68: 2,000 – 6,000 ريال | H68: خبراء + إعداد مواد | I68: 3,000 – 9,000 ريال
C69: ندوات خاصة للمستثمرين | D69: فعاليات حصرية لعرض فرص الاستثمار | E69: 30,000 – 100,000 ريال | F69: منافس لسوق الفعاليات الخاصة | G69: 15,000 – 40,000 ريال | H69: قاعة + تجهيزات + محتوى | I69: 15,000 – 60,000 ريال
C70: تقارير ذكاء الأعمال (BI Reports) | D70: تقارير رقمية تفاعلية عن بيانات اللاعبين والسوق | E70: 20,000 – 50,000 ريال | F70: أسعار مشابهة لمكاتب BI | G70: 8,000 – 20,000 ريال | H70: أدوات BI + فريق تحليل | I70: 12,000 – 30,000 ريال
C71: خدمات Due Diligence | D71: تدقيق وفحص شركات ألعاب قبل الاستثمار | E71: 40,000 – 90,000 ريال | F71: أسعار قريبة من مكاتب المحاماة | G71: 20,000 – 45,000 ريال | H71: محامون + محللون ماليون | I71: 20,000 – 45,000 ريال
C72: إدارة صناديق ألعاب صغيرة | D72: إنشاء وإدارة صناديق استثمارية صغيرة للألعاب | E72: 200,000 – 500,000 ريال | F72: منافس للشركات الاستثمارية الناشئة | G72: 120,000 – 250,000 ريال | H72: إدارة + محاسبة + تقنية | I72: 80,000 – 250,000 ريال
C73: خدمة الوصول المبكر للمشاريع | D73: إعطاء المستثمرين حق الوصول لمشاريع جديدة | E73: 25,000 ريال/اشتراك سنوي | F73: قيمة مضافة لجذب المستثمرين | G73: 10,000 ريال | H73: تشغيل + محتوى حصري | I73: 15,000 ريال
C74: تقارير المخاطر | D74: تحليلات حول مخاطر الاستثمار في الألعاب | E74: 12,000 – 30,000 ريال | F74: أسعار قريبة من الاستشارات المالية | G74: 5,000 – 12,000 ريال | H74: فريق قانوني + مالي | I74: 7,000 – 18,000 ريال
C75: خدمة Pitch Deck | D75: إعداد عروض تقديمية لجذب الاستثمار | E75: 15,000 – 35,000 ريال | F75: مشابه لشركات التسويق | G75: 6,000 – 12,000 ريال | H75: تصميم + محتوى | I75: 9,000 – 23,000 ريال
C76: استضافة جلسات Networking | D76: فعاليات ربط بين مستثمرين ومطورين | E76: 20,000 – 60,000 ريال | F76: شبيه بجلسات حاضنات الأعمال | G76: 10,000 – 25,000 ريال | H76: تنظيم + مكان | I76: 10,000 – 35,000 ريال
C77: ورش عمل استثمارية | D77: ورش حول الاستثمار في صناعة الألعاب | E77: 10,000 – 25,000 ريال | F77: أسعار دورات تخصصية | G77: 4,000 – 10,000 ريال | H77: مدربين + تجهيزات | I77: 6,000 – 15,000 ريال
C78: خدمات قانونية استثمارية | D78: عقود استثمار وحماية ملكية فكرية | E78: 30,000 – 70,000 ريال | F78: أسعار مكاتب قانونية كبرى | G78: 15,000 – 30,000 ريال | H78: محامون + مراجعة | I78: 15,000 – 40,000 ريال
... C85: منصة تواصل للمستثمرين | D85: عضوية في شبكة استثمارية خاصة داخل ماك بلاش | E85: 10,000 ريال/سنة | F85: قيمة رمزية لبناء مجتمع مغلق | G85: 4,000 ريال | H85: إدارة + تقنية + محتوى | I85: 6,000 ريال
C86: تنظيم بطولات وطنية للألعاب الإلكترونية | D86: تخطيط وتنفيذ بطولات رسمية تحت إشراف الحكومة | E86: 500,000 – 2,000,000 ريال/بطولة | F86: أسعار بطولات بحجم Gamers8 | G86: 250,000 – 1,000,000 ريال | H86: تنظيم + جوائز + بث | I86: 250,000 – 1,000,000 ريال | J86: الجهات الحكومية والتنظيمية
C87: إعداد تقارير استراتيجية عن صناعة الألعاب | D87: تقارير سياسات وتوصيات للحكومة | E87: 100,000 – 250,000 ريال/تقرير | F87: أسعار مشابهة لمكاتب استشارية كبرى | G87: 40,000 – 100,000 ريال | H87: فريق بحث + محللين | I87: 60,000 – 150,000 ريال
C88: شراكات مجتمعية شبابية | D88: مبادرات ترفيهية وتعليمية للشباب | E88: 200,000 – 600,000 ريال/مبادرة | F88: سعر منطقي لبرامج اجتماعية | G88: 100,000 – 250,000 ريال | H88: فعاليات + حملات | I88: 100,000 – 350,000 ريال
C89: تطوير منصات تدريبية حكومية | D89: منصات لتعليم صناعة الألعاب | E89: 300,000 – 800,000 ريال | F89: مشابه لمشاريع التدريب الرقمي | G89: 150,000 – 400,000 ريال | H89: تطوير + محتوى | I89: 150,000 – 400,000 ريال
C90: ورش عمل للمعلمين والطلاب | D90: تدريب على الألعاب التعليمية | E90: 50,000 – 150,000 ريال/ورشة | F90: منافس لسوق التدريب الرسمي | G90: 20,000 – 70,000 ريال | H90: مدربين + تجهيزات | I90: 30,000 – 80,000 ريال
C91: إدارة فعاليات عامة | D91: تنظيم مهرجانات ومعارض ترفيهية | E91: 400,000 – 1,200,000 ريال | F91: متماشي مع فعاليات هيئة الترفيه | G91: 200,000 – 600,000 ريال | H91: تنظيم + محتوى | I91: 200,000 – 600,000 ريال
C92: حملات توعية رقمية | D92: حملات توعوية باستخدام الألعاب | E92: 100,000 – 300,000 ريال | F92: شبيه بأسعار الحملات الإعلامية الرسمية | G92: 50,000 – 120,000 ريال | H92: محتوى + منصات | I92: 50,000 – 180,000 ريال
C93: إنتاج محتوى وطني للألعاب | D93: فيديوهات عن الهوية الوطنية بالألعاب | E93: 80,000 – 200,000 ريال | F93: منافس لأسعار الإنتاج الإعلامي | G93: 40,000 – 90,000 ريال | H93: تصوير + مونتاج | I93: 40,000 – 110,000 ريال
C94: شراكات مع المدارس والجامعات | D94: ربط التعليم بالألعاب الإلكترونية | E94: 150,000 – 400,000 ريال/برنامج | F94: منطقي لمشاريع حكومية تعليمية | G94: 70,000 – 200,000 ريال | H94: محتوى + تدريب | I94: 80,000 – 200,000 ريال
C95: أنظمة تتبع الأداء | D95: أنظمة قياس أثر الفعاليات الحكومية | E95: 50,000 – 150,000 ريال | F95: أسعار SaaS حكومية | G95: 20,000 – 60,000 ريال | H95: تطوير + تكامل | I95: 30,000 – 90,000 ريال
C96: محتوى ألعاب تعليمية | D96: تطوير ألعاب مرتبطة بالمناهج | E96: 200,000 – 600,000 ريال | F96: قيمة مناسبة لمشاريع تعليمية كبرى | G96: 100,000 – 300,000 ريال | H96: برمجة + تصميم | I96: 100,000 – 300,000 ريال
C97: منصات حكومية للبث | D97: بث مباشر للفعاليات الوطنية | E97: 150,000 – 400,000 ريال | F97: منافس لسوق البث الرسمي | G97: 70,000 – 200,000 ريال | H97: سيرفرات + فريق تقني | I97: 80,000 – 200,000 ريال
C98: استضافة معارض دولية | D98: تنظيم مشاركة سعودية في معارض مثل E3 | E98: 800,000 – 3,000,000 ريال | F98: أسعار مشاركة حكومية خارجية | G98: 400,000 – 1,500,000 ريال | H98: تنظيم + سفر + تجهيز | I98: 400,000 – 1,500,000 ريال
... C105: محتوى إحصائي دوري | D105: نشر تقارير دورية عن اللاعبين | E105: 60,000 – 120,000 ريال/تقرير | F105: سعر مناسب لتقارير بحثية رسمية | G105: 25,000 – 50,000 ريال | H105: أدوات BI + محللين | I105: 35,000 – 70,000 ريال
C106: تطوير ألعاب تعليمية | D106: برمجة ألعاب تربط المناهج الدراسية بالتفاعل | E106: 150,000 – 400,000 ريال | F106: منافس لسوق الـ Serious Games | G106: 80,000 – 200,000 ريال | H106: برمجة + تصميم + اختبار | I106: 70,000 – 200,000 ريال | J106: المؤسسات التعليمية والثقافية
C107: منصات تدريب على صناعة الألعاب | D107: تطوير منصات تدريبية تفاعلية | E107: 200,000 – 500,000 ريال | F107: مشابه لبرامج الجامعات التقنية | G107: 100,000 – 250,000 ريال | H107: تطوير + محتوى | I107: 100,000 – 250,000 ريال
C108: ورش عمل للطلاب | D108: ورش قصيرة في البرمجة والتصميم | E108: 20,000 – 60,000 ريال/ورشة | F108: أسعار مقبولة للتدريب العملي | G108: 10,000 – 25,000 ريال | H108: مدربين + أدوات | I108: 10,000 – 35,000 ريال
C109: مسابقات جامعية للألعاب | D109: تنظيم بطولات بين الجامعات | E109: 80,000 – 200,000 ريال | F109: قيمة مناسبة لبطولات تعليمية | G109: 40,000 – 100,000 ريال | H109: تنظيم + جوائز | I109: 40,000 – 100,000 ريال
C110: محتوى تعليمي رقمي | D110: مقاطع فيديو ومحاضرات تفاعلية | E110: 10,000 – 25,000 ريال/مادة | F110: أسعار مشابهة للمنصات التعليمية | G110: 4,000 – 10,000 ريال | H110: إنتاج + مونتاج | I110: 6,000 – 15,000 ريال
C111: تدريب معلمي المدارس | D111: تأهيل المعلمين على توظيف الألعاب | E111: 40,000 – 100,000 ريال/برنامج | F111: قيمة معتمدة في التدريب الحكومي | G111: 20,000 – 50,000 ريال | H111: مدربين + قاعات | I111: 20,000 – 50,000 ريال
C112: محتوى ثقافي تفاعلي | D112: ألعاب تعليمية عن التراث والثقافة | E112: 120,000 – 300,000 ريال | F112: مشابه لمشاريع الثقافة الرقمية | G112: 60,000 – 150,000 ريال | H112: برمجة + تصميم | I112: 60,000 – 150,000 ريال
C113: معارض تعليمية للألعاب | D113: تنظيم معارض جامعية لعرض مشاريع الطلاب | E113: 100,000 – 250,000 ريال | F113: سعر مناسب للمعارض الجامعية | G113: 50,000 – 120,000 ريال | H113: تجهيزات + تنظيم | I113: 50,000 – 130,000 ريال
C114: برامج تدريب عن بعد | D114: كورسات Online في تطوير الألعاب | E114: 30,000 – 80,000 ريال | F114: مشابه لسوق منصات E-learning | G114: 15,000 – 35,000 ريال | H114: منصة + محتوى | I114: 15,000 – 45,000 ريال
C115: مكتبة ألعاب رقمية | D115: توفير مكتبة ألعاب تعليمية للمؤسسات | E115: 50,000 – 120,000 ريال | F115: سعر مرن للجامعات والمدارس | G115: 25,000 – 60,000 ريال | H115: تراخيص + منصة | I115: 25,000 – 60,000 ريال
C116: استشارات بحثية | D116: دعم الجامعات بأبحاث سوق الألعاب | E116: 25,000 – 60,000 ريال/تقرير | F116: قريب من أسعار مراكز الدراسات | G116: 10,000 – 25,000 ريال | H116: فريق بحث + أدوات تحليل | I116: 15,000 – 35,000 ريال
C117: مسابقات تطوير الألعاب | D117: هاكاثونات لطلاب الجامعات | E117: 60,000 – 150,000 ريال | F117: قيمة منطقية لمنافسات تقنية | G117: 30,000 – 70,000 ريال | H117: تنظيم + جوائز | I117: 30,000 – 80,000 ريال
C118: محتوى توعوي للطلاب | D118: حملات عن السلوك الرقمي والأمان | E118: 15,000 – 40,000 ريال | F118: مشابه لبرامج التوعية الوطنية | G118: 6,000 – 15,000 ريال | H118: محتوى + حملات | I118: 9,000 – 25,000 ريال
... C126: شراكات بحثية دولية | D126: ربط الجامعات السعودية بجامعات عالمية في مجال الألعاب | E126: 100,000 – 300,000 ريال | F126: قيمة مناسبة لاتفاقيات بحثية | G126: 50,000 – 120,000 ريال | H126: إدارة + محتوى + سفر | I126: 50,000 – 180,000 ريال
C127: فعاليات مجتمعية للألعاب | D127: تنظيم أيام ألعاب مفتوحة للأسر والشباب | E127: 50 – 100 ريال/تذكرة | F127: سعر منخفض يجذب العائلات | G127: 20 – 40 ريال | H127: إيجار موقع + تنظيم | I127: 30 – 60 ريال/شخص | J127: المجتمع العام (الجمهور والأسر)
C128: مهرجانات للألعاب الإلكترونية | D128: مهرجان ترفيهي يضم منصات وتجارب | E128: 100 – 300 ريال/تذكرة | F128: مشابه لفعاليات Gamers8 | G128: 50 – 150 ريال | H128: تنظيم + تجهيزات | I128: 50 – 150 ريال/شخص
C129: باقات عائلية | D129: تذاكر خاصة للعائلات (4–6 أفراد) | E129: 250 – 500 ريال | F129: تشجيع حضور العائلات | G129: 120 – 250 ريال | H129: تنظيم + خدمات ضيافة | I129: 130 – 250 ريال/باقة
C130: تجربة VR/AR ترفيهية | D130: ألعاب واقع افتراضي في المعارض | E130: 20 – 50 ريال/جلسة | F130: سعر معتاد لألعاب VR | G130: 10 – 20 ريال | H130: أجهزة + صيانة | I130: 10 – 30 ريال/جلسة
C131: ورش توعوية للأطفال | D131: تعليم السلوك الرقمي الآمن | E131: 30 – 70 ريال/طفل | F131: سعر مقبول كورش قصيرة | G131: 15 – 30 ريال | H131: مدرب + أدوات | I131: 15 – 40 ريال
C132: مسابقات ميدانية | D132: ألعاب تنافسية في المولات والحدائق | E132: 20 – 50 ريال/مشارك | F132: قيمة رمزية لجذب المشاركين | G132: 10 – 20 ريال | H132: تجهيزات + جوائز | I132: 10 – 30 ريال
C133: تذاكر VIP للفعاليات | D133: تذاكر بميزات إضافية (مقاعد، هدايا) | E133: 500 – 1,000 ريال | F133: تسعير مشابه للـ VIP Events | G133: 250 – 500 ريال | H133: تنظيم + هدايا | I133: 250 – 500 ريال
C134: منتجات تذكارية | D134: بيع قمصان، كابات، مجسمات ماك بلاش | E134: 50 – 200 ريال | F134: قريب من أسعار الميرش في الفعاليات | G134: 20 – 80 ريال | H134: تصنيع + شحن | I134: 30 – 120 ريال
C135: مقاهي ألعاب متنقلة | D135: أكشاك أو عربات تقدم ألعاب وتجارب قصيرة | E135: 20 – 50 ريال/جلسة | F135: سعر مشابه لتجارب المقاهي | G135: 10 – 25 ريال | H135: أجهزة + موقع | I135: 10 – 25 ريال
C136: بطاقات دخول سنوية | D136: بطاقة اشتراك في فعاليات/معارض | E136: 800 – 1,500 ريال | F136: جذابة لهواة الفعاليات | G136: 400 – 700 ريال | H136: تنظيم + منصة | I136: 400 – 800 ريال
C137: جلسات ألعاب عائلية | D137: ألعاب تفاعلية للأسر | E137: 50 – 150 ريال/جلسة | F137: سعر مناسب للأسرة | G137: 25 – 70 ريال | H137: تنظيم + أجهزة | I137: 25 – 80 ريال
C138: تحديات مفتوحة في المولات | D138: تنظيم مسابقات سريعة بجوائز | E138: 10 – 30 ريال/مشارك | F138: قيمة رمزية وسهلة الدفع | G138: 5 – 15 ريال | H138: جوائز + إشراف | I138: 5 – 15 ريال
C139: اشتراكات Kids Club | D139: اشتراك شهري للأطفال للأنشطة التفاعلية | E139: 100 – 200 ريال/شهر | F139: مثل نوادي الأطفال الرقمية | G139: 50 – 100 ريال | H139: محتوى + إشراف | I139: 50 – 100 ريال
...

Sheet الدراسة القانونية 
C3: التشطيب
B4: # | C4: البند | D4: الكمية | E4: السعر | F4: الإجمالي | G4: الملاحضات
B5: المنصة | C5: أتعاب استشارات قانونية سنوية | D5: 12 | E5: 6000 | F5: =E5*D5 -> 72000 | G5: تشمل خدمات مكتب محاماة متخصص لتغطية صياغة عقود الرعايات، الشراكات، عقود الاستثمار، حماية الملكية الفكرية، مراجعة عقود المؤثرين، وتقديم استشارات قانونية دورية.
C6: رسوم تراخيص إعلامية (معلن/إعلامي) | D6: 3 | E6: 3000 | F6: =E6*D6 -> 9000 | G6: استخراج التراخيص الإعلامية والإعلانية من وزارة الإعلام والجهات المختصة لضمان استمرار النشاط وحمايته من الإيقاف.
C7: مصاريف استخراج سجل تجاري | D7: 1 | E7: 2000 | F7: =E7*D7 -> 2000 | G7: تسجيل الشركة بشكل رسمي في وزارة التجارة مع إمكانية توقيع العقود والتعاملات الرسمية مع الجهات الحكومية والخاصة.
C8: تسجيل العلامة التجارية | D8: 1 | E8: 10000 | F8: =E8*D8 -> 10000 | G8: تسجيل وحماية اسم وهوية مشروع ماك بلاش لدى الهيئة السعودية للملكية الفكرية ضد التقليد أو السرقة.
C9: اعداد اللوائح والإجراءات وأفضل الممارسات والمعايير | D9: 1 | E9: 20000 | F9: =E9*D9 -> 20000 | G9: إعداد لوائح داخلية تحدد الحقوق والواجبات، صياغة إجراءات تشغيلية يومية، وضع أفضل الممارسات (Best Practices) وضبط المعايير المحلية والعالمية لضمان الجودة والامتثال.
C10: رسوم التسجيل في الغرفة التجارية | D10: 1 | E10: 5000 | F10: =E10*D10 -> 5000 | G10: اشتراك سنوي إلزامي لجميع الشركات السعودية يتيح الدخول في المناقصات والتعاملات الرسمية.
C11: سياسة حماية البيانات والخصوصية (GDPR/PDPL) | D11: 1 | E11: 15000 | F11: =E11*D11 -> 15000 | G11: صياغة وتنفيذ سياسات حماية البيانات بما يتوافق مع نظام حماية البيانات الشخصية السعودي (PDPL) ومعايير GDPR الدولية.
C12: عقود عمل الموظفين واللائحة الداخلية | D12: 1 | E12: 10000 | F12: =E12*D12 -> 10000 | G12: صياغة عقود عمل قانونية لجميع الموظفين، إعداد لائحة تنظيم العمل معتمدة من وزارة الموارد البشرية، وتسجيل الشركة في البرامج الحكومية (مدد – اعتماد).
C13: إجراءات الامتثال الضريبي (ZATCA) | D13: 4 | E13: 500 | F13: =E13*D13 -> 2000 | G13: تسجيل ضريبة القيمة المضافة (VAT).وإعداد نظام للفوترة الإلكترونية وفق متطلبات هيئة الزكاة.
C14: إجمالي التكاليف الإنشائية | F14: =SUM(F5:F13) -> 145000
C15: إجمالي تكاليف المتر الواحد | F15: =F14/300 -> 483.33333
C16: تكاليف غير مذكورة 15% | F16: =F15*1.15 -> 555.83333
C18: التشطيب | F18: =SUM(F14:F17) -> 146039.17
B19: # | C19: الموارد | D19: العدد | E19: القيمة | F19: الإجمالي
C32: إجمالي التكاليف الإنشائية | F32: =SUM(F20:F31) -> 0
C33: إجمالي تكاليف المتر الواحد | F33: =F32/300 -> 0
C34: تكاليف غير مذكورة 15% | F34: =F33*1.15 -> 0
C37: التشطيب
B38: # | C38: الموارد | D38: العدد | E38: القيمة | F38: الإجمالي
C51: إجمالي التكاليف الإنشائية | F51: =SUM(F39:F50) -> 0
C52: إجمالي تكاليف المتر الواحد | F52: =F51/300 -> 0
C53: تكاليف غير مذكورة 15% | F53: =F52*1.15 -> 0
C57: التشطيب
B58: # | C58: الموارد | D58: العدد | E58: القيمة | F58: الإجمالي
D59: 1 | E59: 300 | F59: =E59*D59 -> 300
D60: 1 | E60: 1000 | F60: =E60*D60 -> 1000
D61: 6 | E61: 1000 | F61: =E61*D61 -> 6000
D62: 1 | E62: 3000 | F62: =E62*D62 -> 3000
D63: 50 | E63: 40 | F63: =E63*D63 -> 2000
D64: 100 | E64: 50 | F64: =E64*D64 -> 5000
D65: 1 | E65: 1500 | F65: =E65*D65 -> 1500
D66: 200 | E66: 15 | F66: =E66*D66 -> 3000
D67: 1 | E67: 2000 | F67: =E67*D67 -> 2000
D68: 150 | E68: 40 | F68: =E68*D68 -> 6000
C71: إجمالي التكاليف الإنشائية | F71: =SUM(F59:F70) -> 29800
C72: إجمالي تكاليف المتر الواحد | F72: =F71/300 -> 99.333333
C73: تكاليف غير مذكورة 15% | F73: =F72*1.15 -> 114.23333

Sheet دراسة الموارد البشرية 
C3: الرواتب المتوقعة بعد الاستقرار | H3: الرواتب المتوقعة في بداية العمل
B4: # | C4: المنصب | D4: العدد | E4: الشهور | F4: الراتب الشهري | G4: الإجمالي | H4: الراتب الشهري | I4: الإجمالي
B5: المنصة | C5: مدير العمليات والتشغيل | D5: 1 | E5: 12 | F5: 15000 | G5: =F5*E5*D5 -> 180000 | H5: =F5/3 -> 5000 | I5: =H5*E5*D5 -> 60000
C6: مدير الإعلام والعلاقات | D6: 1 | E6: 12 | F6: 12000 | G6: =F6*E6*D6 -> 144000 | H6: =F6/3 -> 4000 | I6: =H6*E6*D6 -> 48000
C7: مدير تقنية المعلومات وأمن البيانات | D7: 1 | E7: 12 | F7: 15000 | G7: =F7*E7*D7 -> 180000 | H7: =F7/3 -> 5000 | I7: =H7*E7*D7 -> 60000
C8: مدير البحث والتطوير والابتكار | D8: 1 | E8: 12 | F8: 14000 | G8: =F8*E8*D8 -> 168000 | H8: 4500 | I8: =H8*E8*D8 -> 54000
C9: مدير المالية والمحاسبة والتسويق | D9: 1 | E9: 12 | F9: 12000 | G9: =F9*E9*D9 -> 144000 | H9: =F9/3 -> 4000 | I9: =H9*E9*D9 -> 48000
C10: مدير الموارد البشرية | D10: 1 | E10: 12 | F10: 10000 | G10: =F10*E10*D10 -> 120000 | H10: 3500 | I10: =H10*E10*D10 -> 42000
C11: محلل بيانات | D11: 1 | E11: 12 | F11: 8000 | G11: =F11*E11*D11 -> 96000 | H11: =F11/4 -> 2000 | I11: =H11*E11*D11 -> 24000
C12: مستشار قانوني | D12: 1 | E12: 12 | F12: 12000 | G12: =F12*E12*D12 -> 144000 | H12: =F12/4 -> 3000 | I12: =H12*E12*D12 -> 36000
C13: مطور واجهة المستخدم | D13: 1 | E13: 12 | F13: 10000 | G13: =F13*E13*D13 -> 120000 | H13: =F13/4 -> 2500 | I13: =H13*E13*D13 -> 30000
C14: مطور خلفية | D14: 1 | E14: 12 | F14: 10000 | G14: =F14*E14*D14 -> 120000 | H14: =F14/4 -> 2500 | I14: =H14*E14*D14 -> 30000
C15: مهندس قواعد البيانات | D15: 1 | E15: 12 | F15: 10000 | G15: =F15*E15*D15 -> 120000 | H15: =F15/4 -> 2500 | I15: =H15*E15*D15 -> 30000
C16: مصمم جرافيكي | D16: 1 | E16: 12 | F16: 8000 | G16: =F16*E16*D16 -> 96000 | H16: =F16/4 -> 2000 | I16: =H16*E16*D16 -> 24000
C17: مسؤول دعم فني | D17: 1 | E17: 12 | F17: 6000 | G17: =F17*E17*D17 -> 72000 | H17: 2000 | I17: =H17*E17*D17 -> 24000
C18: مشرف تعاملات مالية | D18: 1 | E18: 12 | F18: 7000 | G18: =F18*E18*D18 -> 84000 | H18: 2000 | I18: =H18*E18*D18 -> 24000
C19: مشرف الألعاب الإلكترونية | D19: 1 | E19: 12 | F19: 7000 | G19: =F19*E19*D19 -> 84000 | H19: 2000 | I19: =H19*E19*D19 -> 24000
C20: مشرف أخبار ومؤتمرات | D20: 1 | E20: 12 | F20: 7000 | G20: =F20*E20*D20 -> 84000 | H20: 2000 | I20: =H20*E20*D20 -> 24000
C21: مشرف التعليم والفعاليات | D21: 1 | E21: 12 | F21: 7000 | G21: =F21*E21*D21 -> 84000 | H21: 2000 | I21: =H21*E21*D21 -> 24000
C22: مراقب تعاملات مالية | D22: 6 | E22: 12 | F22: 5000 | G22: =F22*E22*D22 -> 360000 | H22: 500 | I22: =H22*E22*D22 -> 36000
C23: مراقب الألعاب الإلكترونية | D23: 6 | E23: 12 | F23: 5000 | G23: =F23*E23*D23 -> 360000 | H23: 500 | I23: =H23*E23*D23 -> 36000
C24: مراقب أخبار ومؤتمرات | D24: 6 | E24: 12 | F24: 5000 | G24: =F24*E24*D24 -> 360000 | H24: 500 | I24: =H24*E24*D24 -> 36000
C25: مراقب التعليم والفعاليات | D25: 6 | E25: 12 | F25: 5000 | G25: =F25*E25*D25 -> 360000 | H25: 500 | I25: =H25*E25*D25 -> 36000
C26: إجمالي التكاليف الإنشائية | G26: =SUM(G5:G25) -> 3480000 | I26: =SUM(I5:I25) -> 750000
C27: إجمالي تكاليف المتر الواحد | G27: =G26/300 -> 11600 | I27: =I26/300 -> 2500
C28: تكاليف غير مذكورة 15% | G28: =G27*1.15 -> 13340 | I28: =I27*1.15 -> 2875
C30: التشطيب | G30: =SUM(G24:G29) -> 4224940
B31: # | C31: الموارد | E31: العدد | F31: القيمة | G31: الإجمالي
C44: إجمالي التكاليف الإنشائية | G44: =SUM(G32:G43) -> 0
C45: إجمالي تكاليف المتر الواحد | G45: =G44/300 -> 0
C46: تكاليف غير مذكورة 15% | G46: =G45*1.15 -> 0
C49: التشطيب
B50: # | C50: الموارد | E50: العدد | F50: القيمة | G50: الإجمالي
E51: 1 | F51: 500 | G51: =F51*E51 -> 500
E52: 1 | F52: 3000 | G52: =F52*E52 -> 3000
E53: 6 | F53: 1500 | G53: =F53*E53 -> 9000
E54: 1 | F54: 3000 | G54: =F54*E54 -> 3000
E55: 300 | F55: 140 | G55: =F55*E55 -> 42000
E56: 220 | F56: 50 | G56: =F56*E56 -> 11000
E57: 1 | F57: 2000 | G57: =F57*E57 -> 2000
E58: 400 | F58: 15 | G58: =F58*E58 -> 6000
E59: 1 | F59: 5000 | G59: =F59*E59 -> 5000
E60: 600 | F60: 40 | G60: =F60*E60 -> 24000
C63: إجمالي التكاليف الإنشائية | G63: =SUM(G51:G62) -> 105500
C64: إجمالي تكاليف المتر الواحد | G64: =G63/300 -> 351.66667
C65: تكاليف غير مذكورة 15% | G65: =G64*1.15 -> 404.41667
C69: التشطيب
B70: # | C70: الموارد | E70: العدد | F70: القيمة | G70: الإجمالي
E71: 1 | F71: 300 | G71: =F71*E71 -> 300
E72: 1 | F72: 1000 | G72: =F72*E72 -> 1000
E73: 6 | F73: 1000 | G73: =F73*E73 -> 6000
E74: 1 | F74: 3000 | G74: =F74*E74 -> 3000
E75: 50 | F75: 40 | G75: =F75*E75 -> 2000
E76: 100 | F76: 50 | G76: =F76*E76 -> 5000
E77: 1 | F77: 1500 | G77: =F77*E77 -> 1500
E78: 200 | F78: 15 | G78: =F78*E78 -> 3000
E79: 1 | F79: 2000 | G79: =F79*E79 -> 2000
E80: 150 | F80: 40 | G80: =F80*E80 -> 6000
C83: إجمالي التكاليف الإنشائية | G83: =SUM(G71:G82) -> 29800
C84: إجمالي تكاليف المتر الواحد | G84: =G83/300 -> 99.333333
C85: تكاليف غير مذكورة 15% | G85: =G84*1.15 -> 114.23333

Sheet دراسة الموارد التقنية 
B4: # | C4: البند | D4: العدد | E4: القيمة | F4: الإجمالي | G4: الملاحضات
B5: المنصة | C5: سيرفرات استضافة | D5: 1 | E5: 75000 | F5: =E5*D5 -> 75000 | G5: شراكة مع STC Cloud أو AWS لاستضافة مرنة تدعم مئات الآلاف من المستخدمين.
C6: برامج الأمن السيبراني | D6: 4 | E6: 25000 | F6: =E6*D6 -> 100000 | G6: حلول حماية متقدمة (Firewall, DDoS, SIEM) لضمان حماية المنصة.
C7: برمجة الموقع | D7: 1 | E7: 150000 | F7: =E7*D7 -> 150000 | G7: تطوير موقع متكامل (Marketplace + Gaming Hub + Streaming Integration
C8: نظام بث مباشر | D8: 12 | E8: 5000 | F8: =E8*D8 -> 60000 | G8: أنظمة بث احترافية (Wowza, Agora) + دعم Live Events.
C9: نظام دفع الكتروني | D9: 12 | E9: 3000 | F9: =E9*D9 -> 36000 | G9: تكامل مع مدى، STC Pay، HyperPay (رسوم سنوية + تكاليف الربط).
C10: تكامل API | D10: 4 | E10: 10000 | F10: =E10*D10 -> 40000 | G10: ربط المنصة مع بوابات دفع، واتساب بزنس، منصات ألعاب.
C11: نظام إدارة محتوى (CMS) | D11: 4 | E11: 10000 | F11: =E11*D11 -> 40000 | G11: إدارة المقالات، الفيديوهات، أخبار الألعاب، صفحات خاصة.
C12: أدوات وأنظمة ضبط الجودة ومراقبتها واختبارها | D12: 1 | E12: 3000 | F12: =E12*D12 -> 3000 | G12: أنظمة لمراقبة الأخطاء (Sentry, JMeter, BrowserStack).
C13: دعم الذكاء الصناعي وأتمتة الأعمال | D13: 1 | E13: 45000 | F13: =E13*D13 -> 45000 | G13: استخدام ChatGPT API, BI Tools لتحليل البيانات وأتمتة العمليات
C14: سيرفرات داخلية ونظام تواصل | D14: 1 | E14: 20000 | F14: =E14*D14 -> 20000 | G14: شبكات داخلية، بريد إلكتروني رسمي، سيرفر داخلي للفريق.
C15: دعم العملاء (Chatbot) | D15: 1 | E15: 15000 | F15: =E15*D15 -> 15000 | G15: بوت محادثة متعدد اللغات (Zoho Desk / Intercom).
C16: إنشاء تطبيقات | D16: 2 | E16: 30000 | F16: =E16*D16 -> 60000 | G16: تطبيق iOS + Android متكامل مع المنصة (إعلانات، بث، متجر).
C17: البنية السحابية المرنة | D17: 1 | E17: 10000 | F17: =E17*D17 -> 10000 | G17: خدمات CDN, Auto-Scaling (Cloudflare, AWS CloudFront).
... C21: التراخيص والاشتراكات البرمجية | D21: 12 | E21: 2500 | F21: =E21*D21 -> 30000 | G21: تراخيص أدوات التطوير (Adobe, JetBrains, GitHub Enterprise).
C23: إجمالي التكاليف الإنشائية | F23: =SUM(F5:F22) -> 854000
C24: تكاليف غير مذكورة 15% | F24: =F23*1.15 -> 982100
F26: =SUM(F21:F25) -> 1866100
B27: # | C27: الموارد | D27: العدد | E27: القيمة | F27: الإجمالي
C40: إجمالي التكاليف الإنشائية | F40: =SUM(F28:F39) -> 0
C41: إجمالي تكاليف المتر الواحد | F41: =F40/300 -> 0
C42: تكاليف غير مذكورة 15% | F42: =F41*1.15 -> 0
C45: التشطيب
B46: # | C46: الموارد | D46: العدد | E46: القيمة | F46: الإجمالي
D47: 1 | E47: 500 | F47: =E47*D47 -> 500
D48: 1 | E48: 3000 | F48: =E48*D48 -> 3000
D49: 6 | E49: 1500 | F49: =E49*D49 -> 9000
D50: 1 | E50: 3000 | F50: =E50*D50 -> 3000
D51: 300 | E51: 140 | F51: =E51*D51 -> 42000
D52: 220 | E52: 50 | F52: =E52*D52 -> 11000
D53: 1 | E53: 2000 | F53: =E53*D53 -> 2000
D54: 400 | E54: 15 | F54: =E54*D54 -> 6000
D55: 1 | E55: 5000 | F55: =E55*D55 -> 5000
D56: 600 | E56: 40 | F56: =E56*D56 -> 24000
C59: إجمالي التكاليف الإنشائية | F59: =SUM(F47:F58) -> 105500
C60: إجمالي تكاليف المتر الواحد | F60: =F59/300 -> 351.66667
C61: تكاليف غير مذكورة 15% | F61: =F60*1.15 -> 404.41667
C65: التشطيب
B66: # | C66: الموارد | D66: العدد | E66: القيمة | F66: الإجمالي
D67: 1 | E67: 300 | F67: =E67*D67 -> 300
D68: 1 | E68: 1000 | F68: =E68*D68 -> 1000
D69: 6 | E69: 1000 | F69: =E69*D69 -> 6000
D70: 1 | E70: 3000 | F70: =E70*D70 -> 3000
D71: 50 | E71: 40 | F71: =E71*D71 -> 2000
D72: 100 | E72: 50 | F72: =E72*D72 -> 5000
D73: 1 | E73: 1500 | F73: =E73*D73 -> 1500
D74: 200 | E74: 15 | F74: =E74*D74 -> 3000
D75: 1 | E75: 2000 | F75: =E75*D75 -> 2000
D76: 150 | E76: 40 | F76: =E76*D76 -> 6000
C79: إجمالي التكاليف الإنشائية | F79: =SUM(F67:F78) -> 29800
C80: إجمالي تكاليف المتر الواحد | F80: =F79/300 -> 99.333333
C81: تكاليف غير مذكورة 15% | F81: =F80*1.15 -> 114.23333

Sheet دراسة الموارد اللوجستية  
C3: التشطيب
B4: # | C4: البند | D4: العدد | E4: القيمة | F4: الإجمالي | G4: الملاحضات
B5: المنصة | C5: الموردين وشركاء النقل | D5: 1 | E5: 10000 | F5: =E5*D5 -> 10000 | G5: بناء شبكة علاقات مع شركات النقل المحلية والدولية لضمان سرعة وكفاءة التوصيل.
C6: المخازن والشحنات | D6: 4 | E6: 15000 | F6: =E6*D6 -> 60000 | G6: إيجار وتجهيز مساحات تخزين مؤقتة للأجهزة والمعدات الخاصة بالمنصة والفعاليات.
C7: تأجير النقل والتوصيل | D7: 1 | E7: 15000 | F7: =E7*D7 -> 15000 | G7: استئجار سيارات نقل وتجهيزات لوجستية لدعم عمليات التوصيل محليًا.
C8: الخدمات الجمركية والتخليص | D8: 12 | E8: 2000 | F8: =E8*D8 -> 24000 | G8: مصاريف التخليص الجمركي ورسوم الموانئ للمعدات المستوردة.
C9: لوجستيات الفعاليات والمعارض | D9: 12 | E9: 6000 | F9: =E9*D9 -> 72000 | G9: تجهيز ونقل المعدات والأجهزة للمعارض الكبرى مثل Gamers8 والفعاليات المحلية + تصميم وانشاء البوث
C10: إدارة المخزون | D10: 12 | E10: 2000 | F10: =E10*D10 -> 24000 | G10: نظام إلكتروني لإدارة وتتبع المخزون والموارد (برمجيات + تدريب الموظفين+ الاصول).
C11: إجمالي التكاليف الإنشائية | F11: =SUM(F5:F10) -> 205000
C12: تكاليف غير مذكورة 15% | F12: =F11*1.15 -> 235750
C14: التشطيب | F14: =SUM(F11:F13) -> 440750
B15: # | C15: الموارد | D15: العدد | E15: القيمة | F15: الإجمالي
C28: إجمالي التكاليف الإنشائية | F28: =SUM(F16:F27) -> 0
C29: إجمالي تكاليف المتر الواحد | F29: =F28/300 -> 0
C30: تكاليف غير مذكورة 15% | F30: =F29*1.15 -> 0
C33: التشطيب
B34: # | C34: الموارد | D34: العدد | E34: القيمة | F34: الإجمالي
D35: 1 | E35: 500 | F35: =E35*D35 -> 500
D36: 1 | E36: 3000 | F36: =E36*D36 -> 3000
D37: 6 | E37: 1500 | F37: =E37*D37 -> 9000
D38: 1 | E38: 3000 | F38: =E38*D38 -> 3000
D39: 300 | E39: 140 | F39: =E39*D39 -> 42000
D40: 220 | E40: 50 | F40: =E40*D40 -> 11000
D41: 1 | E41: 2000 | F41: =E41*D41 -> 2000
D42: 400 | E42: 15 | F42: =E42*D42 -> 6000
D43: 1 | E43: 5000 | F43: =E43*D43 -> 5000
D44: 600 | E44: 40 | F44: =E44*D44 -> 24000
C47: إجمالي التكاليف الإنشائية | F47: =SUM(F35:F46) -> 105500
C48: إجمالي تكاليف المتر الواحد | F48: =F47/300 -> 351.66667
C49: تكاليف غير مذكورة 15% | F49: =F48*1.15 -> 404.41667
C53: التشطيب
B54: # | C54: الموارد | D54: العدد | E54: القيمة | F54: الإجمالي
D55: 1 | E55: 300 | F55: =E55*D55 -> 300
D56: 1 | E56: 1000 | F56: =E56*D56 -> 1000
D57: 6 | E57: 1000 | F57: =E57*D57 -> 6000
D58: 1 | E58: 3000 | F58: =E58*D58 -> 3000
D59: 50 | E59: 40 | F59: =E59*D59 -> 2000
D60: 100 | E60: 50 | F60: =E60*D60 -> 5000
D61: 1 | E61: 1500 | F61: =E61*D61 -> 1500
D62: 200 | E62: 15 | F62: =E62*D62 -> 3000
D63: 1 | E63: 2000 | F63: =E63*D63 -> 2000
D64: 150 | E64: 40 | F64: =E64*D64 -> 6000
C67: إجمالي التكاليف الإنشائية | F67: =SUM(F55:F66) -> 29800
C68: إجمالي تكاليف المتر الواحد | F68: =F67/300 -> 99.333333
C69: تكاليف غير مذكورة 15% | F69: =F68*1.15 -> 114.23333

Sheet دراسة الموارد الإدارية  
C3: دراسة الموارد الإدارية - وإدارة المرافق
B4: # | C4: بند | D4: العدد | E4: القيمة | F4: الإجمالي | G4: الإجمالي | H4: الملاحظات
B5: المنصة | C5: استئجار المكتب | D5: 1 | E5: 120000 | F5: =E5*D5 -> 120000 | G5: https://champkit.sa | H5: مساحة مناسبة للفريق (10–30 شخص كبداية).
C6: أثاث مكتبي | D6: 1 | E6: 40000 | F6: =E6*D6 -> 40000 | G6: https://champkit.sa | H6: مكاتب، كراسي، قواطع، غرفة اجتماعات.
C7: ألأجهزة والبرمجيات | D7: 12 | E7: 5000 | F7: =E7*D7 -> 60000 | H7: حواسب، شاشات
C8: الاحتياجات المكتبية | D8: 1 | E8: 5000 | F8: =E8*D8 -> 5000 | H8: قرطاسية، أدوات مكتبية، طابعات.
C9: الخدمات العامة والتأمينات | D9: 12 | E9: 3000 | F9: =E9*D9 -> 36000 | H9: كهرباء، ماء، إنترنت، خدمات حكومية وتعقيب .
C10: إشتراك موقع إدارة المشاريع | D10: 1 | E10: 4600 | F10: =E10*D10 -> 4600 | G10: https://champkit.sa | H10: odoo
C11: إشتراك موقع إدارة المحاسبة والمالية | D11: 1 | E11: 3000 | F11: =E11*D11 -> 3000 | G11: https://elfaleh.sa | H11: وافق
C12: وحدات للسيرفرات والشبكات والتخزينات السحابية | D12: 1 | E12: 120000 | F12: =E12*D12 -> 120000 | H12: تجهيز وحدات خوادم (Servers) داخلية + شبكات إنترنت وشبكة داخلية (LAN/Wi-Fi) + ربط مع التخزين السحابي (Cloud Storage).
C13: استشارات تشغيلية | D13: 4 | E13: 5000 | F13: =E13*D13 -> 20000 | G13: https://champkit.sa | H13: خبراء إدارة وتشغيل لمتابعة الأداء الإداري.
C14: اشتراكات تابعه للذكاء الصناعي | D14: 1 | E14: 15000 | F14: =E14*D14 -> 15000 | G14: https://champkit.sa | H14: ChatGPT Enterprise, Jasper, MidJourney+n8n +hostniger
C15: اشتراك موقع إدارة العملاء | D15: 12 | E15: 2000 | F15: =E15*D15 -> 24000 | G15: https://champkit.sa | H15: zoho crm
C16: إدارة الوثائق والأرشفة | D16: 12 | E16: 500 | F16: =E16*D16 -> 6000 | H16: slack
C17: اشتراكات اتصالات موحدة | D17: 12 | E17: 500 | F17: =E17*D17 -> 6000 | H17: رقام هواتف عمل، بريد إلكتروني رسمي (Microsoft 365 / Google Workspace).
C18: خدمات التنظيف والصيانة الدورية للمكتب | D18: 12 | E18: 1000 | F18: =E18*D18 -> 12000 | H18: نظافة + صيانة أجهزة + أعمال مكتبية.
C19: الصندوق النثري (Petty Cash) | D19: 12 | E19: 2000 | F19: =E19*D19 -> 24000 | H19: مصاريف طارئة يومية (ضيافة، مستلزمات عاجلة، تصليحات).
C20: التدريب الإداري | D20: 4 | E20: 3000 | F20: =E20*D20 -> 12000 | H20: ورش عمل للموظفين على استخدام الأدوات (CRM, ERP).
C21: إجمالي التكاليف الإنشائية | F21: =SUM(F5:F20) -> 507600
C22: المجموع مع التكاليف غير المذكورة 10% | F22: =F21*1.1 -> 558360
C24: اشتراكات
B25: # | C25: البيان | D25: العدد | E25: القيمة | F25: الإجمالي
B26: الإعلامي والفعاليات | G26: https://haraj.com.sa/11122823016/%D9%85%D8%AA%D8%AE%D8%B5%D8%B5%D9%88%D9%86_%D9%81%D9%8A_%D8%AA%D9%88%D8%B1%D9%8A%D8%AF_%D9%88%D8%AA%D8%B1%D9%83%D9%8A%D8%A8_%D8%A7%D8%B1%D8%B6%D9%8A%D8%A7%D8%AA_%D8%A7%D9%84%D8%B1%D8%A8%D8%B1_%D8%A7%D9%84%D8%B5%D8%A8_EPDM_%D9%88%D8%A7%D9%84%D8%A7%D9%83%D8%B1%D9%84%D9%8A%D9%83/
G27: https://www.amazon.sa/%D8%A7%D9%84%D8%A7%D8%AD%D8%AA%D8%B1%D8%A7%D9%81%D9%8A%D8%A9-%D8%A7%D9%84%D9%85%D8%AD%D9%85%D9%88%D9%84%D8%A9-%D8%A7%D9%84%D8%A7%D9%84%D9%88%D9%85%D9%86%D9%8A%D9%88%D9%85-%D9%84%D9%84%D8%AA%D8%B9%D8%AF%D9%8A%D9%84%D8%8C-%D8%A7%D9%84%D8%B1%D8%A7%D9%81%D8%B9%D8%A7%D8%AA%D8%8C/dp/B089CRL17J?th=1
G28: https://banassersport.com/products/Football-Flick-2
C35: إجمالي التكاليف الإنشائية | F35: =SUM(F26:F34) -> 0
C36: المجموع مع التكاليف غير المذكورة 10% | F36: =F35*1.1 -> 0
C39: اشتراكات
B40: # | C40: البيان | D40: العدد | E40: القيمة | F40: الإجمالي
B41: استديو التطوير | G41: https://samnanstore.com/product/%D9%85%D8%B6%D8%AE%D9%87-%D9%85%D8%B3%D8%A8%D8%AD/
G42: https://mawa.com.sa/%D9%81%D9%84%D8%AA%D8%B1-%D9%85%D8%B3%D8%A8%D8%AD-36-%D8%A8%D9%88%D8%B5%D8%A9
C46: إجمالي التكاليف الإنشائية | F46: =SUM(F41:F45) -> 0
C47: المجموع مع التكاليف غير المذكورة 10% | F47: =F46*1.1 -> 0
C51: اشتراكات
B52: # | C52: البيان | D52: العدد | E52: القيمة | F52: الإجمالي
B53: مشاريع أخرى | G53: https://souq-proyard.com/%D8%AA%D8%AC%D9%87%D9%8A%D8%B2-%D9%85%D9%84%D8%A7%D8%B9%D8%A8-%D8%A8%D8%A7%D8%AF%D9%84-47000%D8%A3%D9%84%D9%81-%D8%B1%D9%8A%D8%A7%D9%84-%D8%A8%D8%A7%D9%84%D8%B3%D8%B9%D9%88%D8%AF%D9%8A%D8%A9/p1360615739
C57: إجمالي التكاليف الإنشائية | F57: =SUM(F53:F56) -> 0
C58: المجموع مع التكاليف غير المذكورة 10% | F58: =F57*1.1 -> 0

Sheet الدراسة التسويقية   
B6: # | C6: بند | D6: العدد | E6: القيمة | F6: الإجمالي | G6: الإجمالي | H6: الملاحظات
C7: دراسة تحليلية عن سوق العمل | D7: 1 | E7: 20000 | F7: =E7*D7 -> 20000 | H7: تقرير متخصص لدراسة حجم السوق، المنافسين، وسلوك اللاعبين.
C8: رسوم الاجتماعات التسويقية | D8: 1 | E8: 5000 | F8: =E8*D8 -> 5000 | H8: تكاليف لوجستية لاجتماعات فرق التسويق والتخطيط.
B9: المنصة | C9: إعلانات رقمية | D9: 8 | E9: 50000 | F9: =E9*D9 -> 400000 | G9: https://champkit.sa | H9: حملات عبر Google, Meta, TikTok لاستهداف اللاعبين محليًا ودوليًا.
C10: بوسترات ومطبوعات | D10: 1 | E10: 30000 | F10: =E10*D10 -> 30000 | G10: https://champkit.sa | H10: تصاميم وإنتاج مطبوعات دعائية (بنرات، رول أب، بروشورات).
C11: تقارير انفوجرافيك دورية | D11: 1 | E11: 24000 | F11: =E11*D11 -> 24000 | G11: https://champkit.sa | H11: إعداد تقارير بصرية شهرية حول الأداء والنتائج التسويقية.
C12: فعاليات مرافقة (Booths) | D12: 2 | E12: 25000 | F12: =E12*D12 -> 50000 | G12: https://elfaleh.sa | H12: تأجير وتجهيز منصات عرض في معارض وأحداث كبرى.
C13: تصاميم هوية بصرية والهوية التجارية | D13: 1 | E13: 10000 | F13: =E13*D13 -> 10000 | G13: https://champkit.sa/ | H13: تصميم شعار وهوية كاملة تناسب التوجه العالمي للمنصة.
C14: محتوى تفاعلي (اختبارات، مسابقات عبر الموقع وهدايا ) | D14: 8 | E14: 10000 | F14: =E14*D14 -> 80000 | G14: https://champkit.sa | H14: مسابقات واختبارات عبر الموقع مع جوائز لجذب التفاعل.
C15: صفحة تعريفية بالموقع | D15: 1 | E15: 10000 | F15: =E15*D15 -> 10000 | G15: https://champkit.sa | H15: صفحة تعرض تعريف الشركة، الأهداف والخدمات.
C16: بيانات صحفية | D16: 5 | E16: 5000 | F16: =E16*D16 -> 25000 | G16: https://champkit.sa | H16: نشر أخبار وإعلانات رسمية عبر الصحف والمنصات الإعلامية.
C17: إدارة حسابات رقمية مع الدعم الفني | D17: 5 | E17: 35000 | F17: =E17*D17 -> 175000 | H17: تشغيل حسابات السوشيال ميديا مع الردود والدعم الفني لمدة سنة.
C18: فيديوهات اعلانية عالية الجودة | D18: 8 | E18: 15000 | F18: =E18*D18 -> 120000 | H18: إنتاج فيديوهات إعلانية احترافية (30–90 ثانية).
C19: محتوى مع المؤثرين | D19: 1 | E19: 300000 | F19: =E19*D19 -> 300000 | H19: تعاون مع مشاهير البثوث وصناع المحتوى للألعاب.
C20: رعايات | D20: 3 | E20: 150000 | F20: =E20*D20 -> 450000 | H20: رعاية أحداث ومسابقات إلكترونية للترويج للمنصة.
C21: خطط تسويقية | D21: 1 | E21: 24000 | F21: =E21*D21 -> 24000 | H21: إعداد خطة تسويقية متكاملة (حملات، قنوات، KPIs).
C22: إنتاج بودكاست/برامج دورية عن الألعاب | D22: 12 | E22: 10000 | F22: =E22*D22 -> 120000 | H22: تسجيل ونشر حلقة شهرية (أو أسبوعية في موسم الذروة) عن أحدث الألعاب والاتجاهات.
C23: تحسين محركات البحث (SEO) | D23: 1 | E23: 20000 | F23: =E23*D23 -> 20000 | H23: تهيئة الموقع والمحتوى لنتائج البحث خلال 12 شهر.
C24: الشراكات الاستراتيجية مع مطوري الألعاب | D24: 3 | E24: 100000 | F24: =E24*D24 -> 300000 | H24: اختيار وتدريب لاعبين محليين كممثلين دائمين للمنصة. لتقديم محتوى حصري أو ألعاب مجانية لفترة محدودة.
C25: حملات علاقات عامة | D25: 4 | E25: 20000 | F25: =E25*D25 -> 80000 | H25: قصص نجاح وتغطيات إعلامية موسعة على قنوات التلفاز والصحف
C26: اختبارات وتجارب مستخدم | D26: 12 | E26: 5000 | F26: =E26*D26 -> 60000 | H26: جلسات تجريبية مع لاعبين فعليين واستخلاص ملاحظاتهم لتحسين المنصة.
C27: اشتراك في أدوات قياس الإعلانات وتحليل بيانات الزوار. | D27: 3 | E27: 3000 | F27: =E27*D27 -> 9000 | H27: اشتراكات في منصات تحليل بيانات الزوار والإعلانات.
C28: إجمالي التكاليف الإنشائية | F28: =SUM(F7:F27) -> 2312000
C29: المجموع مع التكاليف غير المذكورة 10% | F29: =F28*1.1 -> 2543200
C31: اشتراكات
B32: # | C32: البيان | D32: العدد | E32: القيمة | F32: الإجمالي
B33: الإعلامي والفعاليات | D33: 1 | E33: 1 | G33: https://haraj.com.sa/11122823016/%D9%85%D8%AA%D8%AE%D8%B5%D8%B5%D9%88%D9%86_%D9%81%D9%8A_%D8%AA%D9%88%D8%B1%D9%8A%D8%AF_%D9%88%D8%AA%D8%B1%D9%83%D9%8A%D8%A8_%D8%A7%D8%B1%D8%B6%D9%8A%D8%A7%D8%AA_%D8%A7%D9%84%D8%B1%D8%A8%D8%B1_%D8%A7%D9%84%D8%B5%D8%A8_EPDM_%D9%88%D8%A7%D9%84%D8%A7%D9%83%D8%B1%D9%84%D9%8A%D9%83/
D34: 1 | E34: 1 | F34: =E34*D34 -> 1 | G34: https://www.amazon.sa/%D8%A7%D9%84%D8%A7%D8%AD%D8%AA%D8%B1%D8%A7%D9%81%D9%8A%D8%A9-%D8%A7%D9%84%D9%85%D8%AD%D9%85%D9%88%D9%84%D8%A9-%D8%A7%D9%84%D8%A7%D9%84%D9%88%D9%85%D9%86%D9%8A%D9%88%D9%85-%D9%84%D9%84%D8%AA%D8%B9%D8%AF%D9%8A%D9%84%D8%8C-%D8%A7%D9%84%D8%B1%D8%A7%D9%81%D8%B9%D8%A7%D8%AA%D8%8C/dp/B089CRL17J?th=1
D35: 1 | E35: 1 | F35: =E35*D35 -> 1 | G35: https://banassersport.com/products/Football-Flick-2
D36: 1 | E36: 1 | F36: =E36*D36 -> 1
D37: 1 | E37: 1 | F37: =E37*D37 -> 1
D38: 1 | E38: 1 | F38: =E38*D38 -> 1
D39: 1 | E39: 1 | F39: =E39*D39 -> 1
D40: 1 | E40: 1 | F40: =E40*D40 -> 1
D41: 1 | E41: 1
C42: إجمالي التكاليف الإنشائية | F42: =SUM(F33:F41) -> 7
C43: المجموع مع التكاليف غير المذكورة 10% | F43: =F42*1.1 -> 7.7
C46: اشتراكات
B47: # | C47: البيان | D47: العدد | E47: القيمة | F47: الإجمالي
B48: استديو التطوير | D48: 1 | E48: 1 | F48: =E48*D48 -> 1 | G48: https://samnanstore.com/product/%D9%85%D8%B6%D8%AE%D9%87-%D9%85%D8%B3%D8%A8%D8%AD/
D49: 1 | E49: 1 | F49: =E49*D49 -> 1 | G49: https://mawa.com.sa/%D9%81%D9%84%D8%AA%D8%B1-%D9%85%D8%B3%D8%A8%D8%AD-36-%D8%A8%D9%88%D8%B5%D8%A9
D50: 1 | E50: 1 | F50: =E50*D50 -> 1
C53: إجمالي التكاليف الإنشائية | F53: =SUM(F48:F52) -> 3
C54: المجموع مع التكاليف غير المذكورة 10% | F54: =F53*1.1 -> 3.3
C58: اشتراكات
B59: # | C59: البيان | D59: العدد | E59: القيمة | F59: الإجمالي
B60: مشاريع أخرى | D60: 1 | E60: 0 | F60: =E60*D60 -> 0 | G60: https://souq-proyard.com/%D8%AA%D8%AC%D9%87%D9%8A%D8%B2-%D9%85%D9%84%D8%A7%D8%B9%D8%A8-%D8%A8%D8%A7%D8%AF%D9%84-47000%D8%A3%D9%84%D9%81-%D8%B1%D9%8A%D8%A7%D9%84-%D8%A8%D8%A7%D9%84%D8%B3%D8%B9%D9%88%D8%AF%D9%8A%D8%A9/p1360615739
D61: 1 | E61: 0 | F61: =E61*D61 -> 0
D62: 1 | E62: 0 | F62: =E62*D62 -> 0
C64: إجمالي التكاليف الإنشائية | F64: =SUM(F60:F63) -> 0
C65: المجموع مع التكاليف غير المذكورة 10% | F65: =F64*1.1 -> 0
